OnlyNandYosysSynth/test/NAND.v
module NAND(
    input wire A,
    input wire B,
    output wire Y
);

assign #1 Y = ~(A&B);

endmodule

OnlyNandYosysSynth/test/synth_counter.v
/* Generated by Yosys 0.9 (git sha1 1979e0b) */

(* top =  1  *)
(* src = "counter.v:1" *)
module counter(clk, rst, count);
  (* src = "counter.v:7" *)
  wire [3:0] _000_;
  wire _001_;
  wire _002_;
  wire _003_;
  wire _004_;
  wire _005_;
  wire _006_;
  wire _007_;
  wire _008_;
  wire _009_;
  wire _010_;
  wire _011_;
  wire _012_;
  wire _013_;
  (* src = "counter.v:7|all2nand.v:18" *)
  wire _014_;
  (* src = "counter.v:7|all2nand.v:21" *)
  wire _015_;
  (* src = "counter.v:7|all2nand.v:24" *)
  wire _016_;
  (* src = "counter.v:7|all2nand.v:24" *)
  wire _017_;
  (* src = "counter.v:7|all2nand.v:22" *)
  wire _018_;
  (* src = "counter.v:7|all2nand.v:15" *)
  wire _019_;
  (* src = "counter.v:7|all2nand.v:16" *)
  wire _020_;
  (* src = "counter.v:7|all2nand.v:26" *)
  wire _021_;
  (* src = "counter.v:7|all2nand.v:26" *)
  wire _022_;
  (* src = "counter.v:7|all2nand.v:26" *)
  wire _023_;
  (* src = "counter.v:7|all2nand.v:26" *)
  wire _024_;
  (* src = "counter.v:7|all2nand.v:27" *)
  wire _025_;
  (* src = "counter.v:7|all2nand.v:27" *)
  wire _026_;
  (* src = "counter.v:7|all2nand.v:27" *)
  wire _027_;
  (* src = "counter.v:7|all2nand.v:27" *)
  wire _028_;
  (* src = "counter.v:7|all2nand.v:17" *)
  wire _029_;
  (* src = "counter.v:7|all2nand.v:24" *)
  wire _030_;
  (* src = "counter.v:7|all2nand.v:25" *)
  wire _031_;
  (* src = "counter.v:7|all2nand.v:25" *)
  wire _032_;
  (* src = "counter.v:7|all2nand.v:18" *)
  wire _033_;
  (* src = "counter.v:7|all2nand.v:21" *)
  wire _034_;
  (* src = "counter.v:7|all2nand.v:24" *)
  wire _035_;
  (* src = "counter.v:7|all2nand.v:24" *)
  wire _036_;
  (* src = "counter.v:7|all2nand.v:22" *)
  wire _037_;
  (* src = "counter.v:7|all2nand.v:15" *)
  wire _038_;
  (* src = "counter.v:7|all2nand.v:16" *)
  wire _039_;
  (* src = "counter.v:7|all2nand.v:26" *)
  wire _040_;
  (* src = "counter.v:7|all2nand.v:26" *)
  wire _041_;
  (* src = "counter.v:7|all2nand.v:26" *)
  wire _042_;
  (* src = "counter.v:7|all2nand.v:26" *)
  wire _043_;
  (* src = "counter.v:7|all2nand.v:27" *)
  wire _044_;
  (* src = "counter.v:7|all2nand.v:27" *)
  wire _045_;
  (* src = "counter.v:7|all2nand.v:27" *)
  wire _046_;
  (* src = "counter.v:7|all2nand.v:27" *)
  wire _047_;
  (* src = "counter.v:7|all2nand.v:17" *)
  wire _048_;
  (* src = "counter.v:7|all2nand.v:24" *)
  wire _049_;
  (* src = "counter.v:7|all2nand.v:25" *)
  wire _050_;
  (* src = "counter.v:7|all2nand.v:25" *)
  wire _051_;
  (* src = "counter.v:7|all2nand.v:18" *)
  wire _052_;
  (* src = "counter.v:7|all2nand.v:21" *)
  wire _053_;
  (* src = "counter.v:7|all2nand.v:24" *)
  wire _054_;
  (* src = "counter.v:7|all2nand.v:24" *)
  wire _055_;
  (* src = "counter.v:7|all2nand.v:22" *)
  wire _056_;
  (* src = "counter.v:7|all2nand.v:15" *)
  wire _057_;
  (* src = "counter.v:7|all2nand.v:16" *)
  wire _058_;
  (* src = "counter.v:7|all2nand.v:26" *)
  wire _059_;
  (* src = "counter.v:7|all2nand.v:26" *)
  wire _060_;
  (* src = "counter.v:7|all2nand.v:26" *)
  wire _061_;
  (* src = "counter.v:7|all2nand.v:26" *)
  wire _062_;
  (* src = "counter.v:7|all2nand.v:27" *)
  wire _063_;
  (* src = "counter.v:7|all2nand.v:27" *)
  wire _064_;
  (* src = "counter.v:7|all2nand.v:27" *)
  wire _065_;
  (* src = "counter.v:7|all2nand.v:27" *)
  wire _066_;
  (* src = "counter.v:7|all2nand.v:17" *)
  wire _067_;
  (* src = "counter.v:7|all2nand.v:24" *)
  wire _068_;
  (* src = "counter.v:7|all2nand.v:25" *)
  wire _069_;
  (* src = "counter.v:7|all2nand.v:25" *)
  wire _070_;
  (* src = "counter.v:7|all2nand.v:18" *)
  wire _071_;
  (* src = "counter.v:7|all2nand.v:21" *)
  wire _072_;
  (* src = "counter.v:7|all2nand.v:24" *)
  wire _073_;
  (* src = "counter.v:7|all2nand.v:24" *)
  wire _074_;
  (* src = "counter.v:7|all2nand.v:22" *)
  wire _075_;
  (* src = "counter.v:7|all2nand.v:15" *)
  wire _076_;
  (* src = "counter.v:7|all2nand.v:16" *)
  wire _077_;
  (* src = "counter.v:7|all2nand.v:26" *)
  wire _078_;
  (* src = "counter.v:7|all2nand.v:26" *)
  wire _079_;
  (* src = "counter.v:7|all2nand.v:26" *)
  wire _080_;
  (* src = "counter.v:7|all2nand.v:26" *)
  wire _081_;
  (* src = "counter.v:7|all2nand.v:27" *)
  wire _082_;
  (* src = "counter.v:7|all2nand.v:27" *)
  wire _083_;
  (* src = "counter.v:7|all2nand.v:27" *)
  wire _084_;
  (* src = "counter.v:7|all2nand.v:27" *)
  wire _085_;
  (* src = "counter.v:7|all2nand.v:17" *)
  wire _086_;
  (* src = "counter.v:7|all2nand.v:24" *)
  wire _087_;
  (* src = "counter.v:7|all2nand.v:25" *)
  wire _088_;
  (* src = "counter.v:7|all2nand.v:25" *)
  wire _089_;
  (* src = "counter.v:2" *)
  input clk;
  (* src = "counter.v:4" *)
  output [3:0] count;
  (* src = "counter.v:3" *)
  input rst;
  (* module_not_derived = 32'd1 *)
  (* src = "all2nand.v:3" *)
  NAND _090_ (
    .A(count[1]),
    .B(count[1]),
    .Y(_013_)
  );
  (* module_not_derived = 32'd1 *)
  (* src = "all2nand.v:3" *)
  NAND _091_ (
    .A(count[0]),
    .B(count[0]),
    .Y(_000_[0])
  );
  (* module_not_derived = 32'd1 *)
  (* src = "all2nand.v:3" *)
  NAND _092_ (
    .A(count[2]),
    .B(count[2]),
    .Y(_001_)
  );
  (* module_not_derived = 32'd1 *)
  (* src = "all2nand.v:3" *)
  NAND _093_ (
    .A(count[3]),
    .B(count[3]),
    .Y(_002_)
  );
  NAND _094_ (
    .A(count[1]),
    .B(count[0]),
    .Y(_003_)
  );
  (* module_not_derived = 32'd1 *)
  (* src = "all2nand.v:3" *)
  NAND _095_ (
    .A(_003_),
    .B(_003_),
    .Y(_004_)
  );
  NAND _096_ (
    .A(_013_),
    .B(_000_[0]),
    .Y(_005_)
  );
  NAND _097_ (
    .A(_003_),
    .B(_005_),
    .Y(_006_)
  );
  (* module_not_derived = 32'd1 *)
  (* src = "all2nand.v:3" *)
  NAND _098_ (
    .A(_006_),
    .B(_006_),
    .Y(_000_[1])
  );
  NAND _099_ (
    .A(count[2]),
    .B(_004_),
    .Y(_007_)
  );
  (* module_not_derived = 32'd1 *)
  (* src = "all2nand.v:3" *)
  NAND _100_ (
    .A(_007_),
    .B(_007_),
    .Y(_008_)
  );
  NAND _101_ (
    .A(_001_),
    .B(_003_),
    .Y(_009_)
  );
  NAND _102_ (
    .A(_007_),
    .B(_009_),
    .Y(_010_)
  );
  (* module_not_derived = 32'd1 *)
  (* src = "all2nand.v:3" *)
  NAND _103_ (
    .A(_010_),
    .B(_010_),
    .Y(_000_[2])
  );
  NAND _104_ (
    .A(count[3]),
    .B(_007_),
    .Y(_011_)
  );
  NAND _105_ (
    .A(_002_),
    .B(_008_),
    .Y(_012_)
  );
  NAND _106_ (
    .A(_011_),
    .B(_012_),
    .Y(_000_[3])
  );
  (* module_not_derived = 32'd1 *)
  (* src = "counter.v:7|all2nand.v:53|all2nand.v:3" *)
  NAND _107_ (
    .A(_018_),
    .B(_018_),
    .Y(_029_)
  );
  (* module_not_derived = 32'd1 *)
  (* src = "counter.v:7|all2nand.v:39|all2nand.v:3" *)
  NAND _108_ (
    .A(_025_),
    .B(_025_),
    .Y(_026_)
  );
  (* module_not_derived = 32'd1 *)
  (* src = "counter.v:7|all2nand.v:40|all2nand.v:3" *)
  NAND _109_ (
    .A(_026_),
    .B(_026_),
    .Y(_027_)
  );
  (* module_not_derived = 32'd1 *)
  (* src = "counter.v:7|all2nand.v:41|all2nand.v:3" *)
  NAND _110_ (
    .A(_027_),
    .B(_027_),
    .Y(_028_)
  );
  (* module_not_derived = 32'd1 *)
  (* src = "counter.v:7|all2nand.v:43|all2nand.v:3" *)
  NAND _111_ (
    .A(_031_),
    .B(_031_),
    .Y(_032_)
  );
  (* module_not_derived = 32'd1 *)
  (* src = "counter.v:7|all2nand.v:47|all2nand.v:3" *)
  NAND _112_ (
    .A(_015_),
    .B(_015_),
    .Y(_018_)
  );
  (* module_not_derived = 32'd1 *)
  (* src = "counter.v:7|all2nand.v:30|all2nand.v:3" *)
  NAND _113_ (
    .A(clk),
    .B(clk),
    .Y(_021_)
  );
  (* module_not_derived = 32'd1 *)
  (* src = "counter.v:7|all2nand.v:31|all2nand.v:3" *)
  NAND _114_ (
    .A(_021_),
    .B(_021_),
    .Y(_022_)
  );
  (* module_not_derived = 32'd1 *)
  (* src = "counter.v:7|all2nand.v:32|all2nand.v:3" *)
  NAND _115_ (
    .A(_022_),
    .B(_022_),
    .Y(_023_)
  );
  (* module_not_derived = 32'd1 *)
  (* src = "counter.v:7|all2nand.v:34|all2nand.v:3" *)
  NAND _116_ (
    .A(_030_),
    .B(_030_),
    .Y(_016_)
  );
  (* module_not_derived = 32'd1 *)
  (* src = "counter.v:7|all2nand.v:37|all2nand.v:3" *)
  NAND _117_ (
    .A(rst),
    .B(rst),
    .Y(_024_)
  );
  (* module_not_derived = 32'd1 *)
  (* src = "counter.v:7|all2nand.v:38|all2nand.v:3" *)
  NAND _118_ (
    .A(_024_),
    .B(_024_),
    .Y(_025_)
  );
  (* module_not_derived = 32'd1 *)
  (* src = "counter.v:7|all2nand.v:54" *)
  NAND _119_ (
    .A(_017_),
    .B(_018_),
    .Y(_019_)
  );
  (* module_not_derived = 32'd1 *)
  (* src = "counter.v:7|all2nand.v:55" *)
  NAND _120_ (
    .A(_017_),
    .B(_029_),
    .Y(_020_)
  );
  (* module_not_derived = 32'd1 *)
  (* src = "counter.v:7|all2nand.v:56" *)
  NAND _121_ (
    .A(_019_),
    .B(_014_),
    .Y(count[0])
  );
  (* module_not_derived = 32'd1 *)
  (* src = "counter.v:7|all2nand.v:57" *)
  NAND _122_ (
    .A(_020_),
    .B(count[0]),
    .Y(_014_)
  );
  (* module_not_derived = 32'd1 *)
  (* src = "counter.v:7|all2nand.v:33" *)
  NAND _123_ (
    .A(_023_),
    .B(clk),
    .Y(_030_)
  );
  (* module_not_derived = 32'd1 *)
  (* src = "counter.v:7|all2nand.v:42" *)
  NAND _124_ (
    .A(_028_),
    .B(rst),
    .Y(_031_)
  );
  (* module_not_derived = 32'd1 *)
  (* src = "counter.v:7|all2nand.v:46" *)
  NAND _125_ (
    .A(_031_),
    .B(_000_[0]),
    .Y(_015_)
  );
  (* module_not_derived = 32'd1 *)
  (* src = "counter.v:7|all2nand.v:50" *)
  NAND _126_ (
    .A(_031_),
    .B(_030_),
    .Y(_017_)
  );
  (* module_not_derived = 32'd1 *)
  (* src = "counter.v:7|all2nand.v:53|all2nand.v:3" *)
  NAND _127_ (
    .A(_037_),
    .B(_037_),
    .Y(_048_)
  );
  (* module_not_derived = 32'd1 *)
  (* src = "counter.v:7|all2nand.v:39|all2nand.v:3" *)
  NAND _128_ (
    .A(_044_),
    .B(_044_),
    .Y(_045_)
  );
  (* module_not_derived = 32'd1 *)
  (* src = "counter.v:7|all2nand.v:40|all2nand.v:3" *)
  NAND _129_ (
    .A(_045_),
    .B(_045_),
    .Y(_046_)
  );
  (* module_not_derived = 32'd1 *)
  (* src = "counter.v:7|all2nand.v:41|all2nand.v:3" *)
  NAND _130_ (
    .A(_046_),
    .B(_046_),
    .Y(_047_)
  );
  (* module_not_derived = 32'd1 *)
  (* src = "counter.v:7|all2nand.v:43|all2nand.v:3" *)
  NAND _131_ (
    .A(_050_),
    .B(_050_),
    .Y(_051_)
  );
  (* module_not_derived = 32'd1 *)
  (* src = "counter.v:7|all2nand.v:47|all2nand.v:3" *)
  NAND _132_ (
    .A(_034_),
    .B(_034_),
    .Y(_037_)
  );
  (* module_not_derived = 32'd1 *)
  (* src = "counter.v:7|all2nand.v:30|all2nand.v:3" *)
  NAND _133_ (
    .A(clk),
    .B(clk),
    .Y(_040_)
  );
  (* module_not_derived = 32'd1 *)
  (* src = "counter.v:7|all2nand.v:31|all2nand.v:3" *)
  NAND _134_ (
    .A(_040_),
    .B(_040_),
    .Y(_041_)
  );
  (* module_not_derived = 32'd1 *)
  (* src = "counter.v:7|all2nand.v:32|all2nand.v:3" *)
  NAND _135_ (
    .A(_041_),
    .B(_041_),
    .Y(_042_)
  );
  (* module_not_derived = 32'd1 *)
  (* src = "counter.v:7|all2nand.v:34|all2nand.v:3" *)
  NAND _136_ (
    .A(_049_),
    .B(_049_),
    .Y(_035_)
  );
  (* module_not_derived = 32'd1 *)
  (* src = "counter.v:7|all2nand.v:37|all2nand.v:3" *)
  NAND _137_ (
    .A(rst),
    .B(rst),
    .Y(_043_)
  );
  (* module_not_derived = 32'd1 *)
  (* src = "counter.v:7|all2nand.v:38|all2nand.v:3" *)
  NAND _138_ (
    .A(_043_),
    .B(_043_),
    .Y(_044_)
  );
  (* module_not_derived = 32'd1 *)
  (* src = "counter.v:7|all2nand.v:54" *)
  NAND _139_ (
    .A(_036_),
    .B(_037_),
    .Y(_038_)
  );
  (* module_not_derived = 32'd1 *)
  (* src = "counter.v:7|all2nand.v:55" *)
  NAND _140_ (
    .A(_036_),
    .B(_048_),
    .Y(_039_)
  );
  (* module_not_derived = 32'd1 *)
  (* src = "counter.v:7|all2nand.v:56" *)
  NAND _141_ (
    .A(_038_),
    .B(_033_),
    .Y(count[1])
  );
  (* module_not_derived = 32'd1 *)
  (* src = "counter.v:7|all2nand.v:57" *)
  NAND _142_ (
    .A(_039_),
    .B(count[1]),
    .Y(_033_)
  );
  (* module_not_derived = 32'd1 *)
  (* src = "counter.v:7|all2nand.v:33" *)
  NAND _143_ (
    .A(_042_),
    .B(clk),
    .Y(_049_)
  );
  (* module_not_derived = 32'd1 *)
  (* src = "counter.v:7|all2nand.v:42" *)
  NAND _144_ (
    .A(_047_),
    .B(rst),
    .Y(_050_)
  );
  (* module_not_derived = 32'd1 *)
  (* src = "counter.v:7|all2nand.v:46" *)
  NAND _145_ (
    .A(_050_),
    .B(_000_[1]),
    .Y(_034_)
  );
  (* module_not_derived = 32'd1 *)
  (* src = "counter.v:7|all2nand.v:50" *)
  NAND _146_ (
    .A(_050_),
    .B(_049_),
    .Y(_036_)
  );
  (* module_not_derived = 32'd1 *)
  (* src = "counter.v:7|all2nand.v:53|all2nand.v:3" *)
  NAND _147_ (
    .A(_056_),
    .B(_056_),
    .Y(_067_)
  );
  (* module_not_derived = 32'd1 *)
  (* src = "counter.v:7|all2nand.v:39|all2nand.v:3" *)
  NAND _148_ (
    .A(_063_),
    .B(_063_),
    .Y(_064_)
  );
  (* module_not_derived = 32'd1 *)
  (* src = "counter.v:7|all2nand.v:40|all2nand.v:3" *)
  NAND _149_ (
    .A(_064_),
    .B(_064_),
    .Y(_065_)
  );
  (* module_not_derived = 32'd1 *)
  (* src = "counter.v:7|all2nand.v:41|all2nand.v:3" *)
  NAND _150_ (
    .A(_065_),
    .B(_065_),
    .Y(_066_)
  );
  (* module_not_derived = 32'd1 *)
  (* src = "counter.v:7|all2nand.v:43|all2nand.v:3" *)
  NAND _151_ (
    .A(_069_),
    .B(_069_),
    .Y(_070_)
  );
  (* module_not_derived = 32'd1 *)
  (* src = "counter.v:7|all2nand.v:47|all2nand.v:3" *)
  NAND _152_ (
    .A(_053_),
    .B(_053_),
    .Y(_056_)
  );
  (* module_not_derived = 32'd1 *)
  (* src = "counter.v:7|all2nand.v:30|all2nand.v:3" *)
  NAND _153_ (
    .A(clk),
    .B(clk),
    .Y(_059_)
  );
  (* module_not_derived = 32'd1 *)
  (* src = "counter.v:7|all2nand.v:31|all2nand.v:3" *)
  NAND _154_ (
    .A(_059_),
    .B(_059_),
    .Y(_060_)
  );
  (* module_not_derived = 32'd1 *)
  (* src = "counter.v:7|all2nand.v:32|all2nand.v:3" *)
  NAND _155_ (
    .A(_060_),
    .B(_060_),
    .Y(_061_)
  );
  (* module_not_derived = 32'd1 *)
  (* src = "counter.v:7|all2nand.v:34|all2nand.v:3" *)
  NAND _156_ (
    .A(_068_),
    .B(_068_),
    .Y(_054_)
  );
  (* module_not_derived = 32'd1 *)
  (* src = "counter.v:7|all2nand.v:37|all2nand.v:3" *)
  NAND _157_ (
    .A(rst),
    .B(rst),
    .Y(_062_)
  );
  (* module_not_derived = 32'd1 *)
  (* src = "counter.v:7|all2nand.v:38|all2nand.v:3" *)
  NAND _158_ (
    .A(_062_),
    .B(_062_),
    .Y(_063_)
  );
  (* module_not_derived = 32'd1 *)
  (* src = "counter.v:7|all2nand.v:54" *)
  NAND _159_ (
    .A(_055_),
    .B(_056_),
    .Y(_057_)
  );
  (* module_not_derived = 32'd1 *)
  (* src = "counter.v:7|all2nand.v:55" *)
  NAND _160_ (
    .A(_055_),
    .B(_067_),
    .Y(_058_)
  );
  (* module_not_derived = 32'd1 *)
  (* src = "counter.v:7|all2nand.v:56" *)
  NAND _161_ (
    .A(_057_),
    .B(_052_),
    .Y(count[2])
  );
  (* module_not_derived = 32'd1 *)
  (* src = "counter.v:7|all2nand.v:57" *)
  NAND _162_ (
    .A(_058_),
    .B(count[2]),
    .Y(_052_)
  );
  (* module_not_derived = 32'd1 *)
  (* src = "counter.v:7|all2nand.v:33" *)
  NAND _163_ (
    .A(_061_),
    .B(clk),
    .Y(_068_)
  );
  (* module_not_derived = 32'd1 *)
  (* src = "counter.v:7|all2nand.v:42" *)
  NAND _164_ (
    .A(_066_),
    .B(rst),
    .Y(_069_)
  );
  (* module_not_derived = 32'd1 *)
  (* src = "counter.v:7|all2nand.v:46" *)
  NAND _165_ (
    .A(_069_),
    .B(_000_[2]),
    .Y(_053_)
  );
  (* module_not_derived = 32'd1 *)
  (* src = "counter.v:7|all2nand.v:50" *)
  NAND _166_ (
    .A(_069_),
    .B(_068_),
    .Y(_055_)
  );
  (* module_not_derived = 32'd1 *)
  (* src = "counter.v:7|all2nand.v:53|all2nand.v:3" *)
  NAND _167_ (
    .A(_075_),
    .B(_075_),
    .Y(_086_)
  );
  (* module_not_derived = 32'd1 *)
  (* src = "counter.v:7|all2nand.v:39|all2nand.v:3" *)
  NAND _168_ (
    .A(_082_),
    .B(_082_),
    .Y(_083_)
  );
  (* module_not_derived = 32'd1 *)
  (* src = "counter.v:7|all2nand.v:40|all2nand.v:3" *)
  NAND _169_ (
    .A(_083_),
    .B(_083_),
    .Y(_084_)
  );
  (* module_not_derived = 32'd1 *)
  (* src = "counter.v:7|all2nand.v:41|all2nand.v:3" *)
  NAND _170_ (
    .A(_084_),
    .B(_084_),
    .Y(_085_)
  );
  (* module_not_derived = 32'd1 *)
  (* src = "counter.v:7|all2nand.v:43|all2nand.v:3" *)
  NAND _171_ (
    .A(_088_),
    .B(_088_),
    .Y(_089_)
  );
  (* module_not_derived = 32'd1 *)
  (* src = "counter.v:7|all2nand.v:47|all2nand.v:3" *)
  NAND _172_ (
    .A(_072_),
    .B(_072_),
    .Y(_075_)
  );
  (* module_not_derived = 32'd1 *)
  (* src = "counter.v:7|all2nand.v:30|all2nand.v:3" *)
  NAND _173_ (
    .A(clk),
    .B(clk),
    .Y(_078_)
  );
  (* module_not_derived = 32'd1 *)
  (* src = "counter.v:7|all2nand.v:31|all2nand.v:3" *)
  NAND _174_ (
    .A(_078_),
    .B(_078_),
    .Y(_079_)
  );
  (* module_not_derived = 32'd1 *)
  (* src = "counter.v:7|all2nand.v:32|all2nand.v:3" *)
  NAND _175_ (
    .A(_079_),
    .B(_079_),
    .Y(_080_)
  );
  (* module_not_derived = 32'd1 *)
  (* src = "counter.v:7|all2nand.v:34|all2nand.v:3" *)
  NAND _176_ (
    .A(_087_),
    .B(_087_),
    .Y(_073_)
  );
  (* module_not_derived = 32'd1 *)
  (* src = "counter.v:7|all2nand.v:37|all2nand.v:3" *)
  NAND _177_ (
    .A(rst),
    .B(rst),
    .Y(_081_)
  );
  (* module_not_derived = 32'd1 *)
  (* src = "counter.v:7|all2nand.v:38|all2nand.v:3" *)
  NAND _178_ (
    .A(_081_),
    .B(_081_),
    .Y(_082_)
  );
  (* module_not_derived = 32'd1 *)
  (* src = "counter.v:7|all2nand.v:54" *)
  NAND _179_ (
    .A(_074_),
    .B(_075_),
    .Y(_076_)
  );
  (* module_not_derived = 32'd1 *)
  (* src = "counter.v:7|all2nand.v:55" *)
  NAND _180_ (
    .A(_074_),
    .B(_086_),
    .Y(_077_)
  );
  (* module_not_derived = 32'd1 *)
  (* src = "counter.v:7|all2nand.v:56" *)
  NAND _181_ (
    .A(_076_),
    .B(_071_),
    .Y(count[3])
  );
  (* module_not_derived = 32'd1 *)
  (* src = "counter.v:7|all2nand.v:57" *)
  NAND _182_ (
    .A(_077_),
    .B(count[3]),
    .Y(_071_)
  );
  (* module_not_derived = 32'd1 *)
  (* src = "counter.v:7|all2nand.v:33" *)
  NAND _183_ (
    .A(_080_),
    .B(clk),
    .Y(_087_)
  );
  (* module_not_derived = 32'd1 *)
  (* src = "counter.v:7|all2nand.v:42" *)
  NAND _184_ (
    .A(_085_),
    .B(rst),
    .Y(_088_)
  );
  (* module_not_derived = 32'd1 *)
  (* src = "counter.v:7|all2nand.v:46" *)
  NAND _185_ (
    .A(_088_),
    .B(_000_[3]),
    .Y(_072_)
  );
  (* module_not_derived = 32'd1 *)
  (* src = "counter.v:7|all2nand.v:50" *)
  NAND _186_ (
    .A(_088_),
    .B(_087_),
    .Y(_074_)
  );
endmodule

OnlyNandYosysSynth/test/counter_tb.v
//iverilog -o .\out\counter_tb .\counter_tb.v .\synth_counter.v .\DFF_PP0.v .\NOT.v .\NAND.v
module counter_tb;
    reg clk, reset;
    wire [3:0] counter;

    counter count(clk, reset, counter);
    
    initial begin
        clk=0;
        forever #50 clk=~clk;
    end

    initial begin
        $dumpfile("counter.vcd");
        $dumpvars(1,count, clk);
        $display("start");
        reset = 0;
        #500
        reset=1;
        #500;
        reset=0;
        #5000;
        $display("finish");
        $finish;
    end
endmodule

OnlyNandYosysSynth/test/out/counter.vcd
$date
	Fri Aug 25 12:16:37 2023
$end
$version
	Icarus Verilog
$end
$timescale
	1s
$end
$scope module counter_tb $end
$scope module count $end
$var wire 1 ! clk $end
$var wire 1 " rst $end
$var wire 4 # count [3:0] $end
$var wire 1 $ _089_ $end
$var wire 1 % _088_ $end
$var wire 1 & _087_ $end
$var wire 1 ' _086_ $end
$var wire 1 ( _085_ $end
$var wire 1 ) _084_ $end
$var wire 1 * _083_ $end
$var wire 1 + _082_ $end
$var wire 1 , _081_ $end
$var wire 1 - _080_ $end
$var wire 1 . _079_ $end
$var wire 1 / _078_ $end
$var wire 1 0 _077_ $end
$var wire 1 1 _076_ $end
$var wire 1 2 _075_ $end
$var wire 1 3 _074_ $end
$var wire 1 4 _073_ $end
$var wire 1 5 _072_ $end
$var wire 1 6 _071_ $end
$var wire 1 7 _070_ $end
$var wire 1 8 _069_ $end
$var wire 1 9 _068_ $end
$var wire 1 : _067_ $end
$var wire 1 ; _066_ $end
$var wire 1 < _065_ $end
$var wire 1 = _064_ $end
$var wire 1 > _063_ $end
$var wire 1 ? _062_ $end
$var wire 1 @ _061_ $end
$var wire 1 A _060_ $end
$var wire 1 B _059_ $end
$var wire 1 C _058_ $end
$var wire 1 D _057_ $end
$var wire 1 E _056_ $end
$var wire 1 F _055_ $end
$var wire 1 G _054_ $end
$var wire 1 H _053_ $end
$var wire 1 I _052_ $end
$var wire 1 J _051_ $end
$var wire 1 K _050_ $end
$var wire 1 L _049_ $end
$var wire 1 M _048_ $end
$var wire 1 N _047_ $end
$var wire 1 O _046_ $end
$var wire 1 P _045_ $end
$var wire 1 Q _044_ $end
$var wire 1 R _043_ $end
$var wire 1 S _042_ $end
$var wire 1 T _041_ $end
$var wire 1 U _040_ $end
$var wire 1 V _039_ $end
$var wire 1 W _038_ $end
$var wire 1 X _037_ $end
$var wire 1 Y _036_ $end
$var wire 1 Z _035_ $end
$var wire 1 [ _034_ $end
$var wire 1 \ _033_ $end
$var wire 1 ] _032_ $end
$var wire 1 ^ _031_ $end
$var wire 1 _ _030_ $end
$var wire 1 ` _029_ $end
$var wire 1 a _028_ $end
$var wire 1 b _027_ $end
$var wire 1 c _026_ $end
$var wire 1 d _025_ $end
$var wire 1 e _024_ $end
$var wire 1 f _023_ $end
$var wire 1 g _022_ $end
$var wire 1 h _021_ $end
$var wire 1 i _020_ $end
$var wire 1 j _019_ $end
$var wire 1 k _018_ $end
$var wire 1 l _017_ $end
$var wire 1 m _016_ $end
$var wire 1 n _015_ $end
$var wire 1 o _014_ $end
$var wire 1 p _013_ $end
$var wire 1 q _012_ $end
$var wire 1 r _011_ $end
$var wire 1 s _010_ $end
$var wire 1 t _009_ $end
$var wire 1 u _008_ $end
$var wire 1 v _007_ $end
$var wire 1 w _006_ $end
$var wire 1 x _005_ $end
$var wire 1 y _004_ $end
$var wire 1 z _003_ $end
$var wire 1 { _002_ $end
$var wire 1 | _001_ $end
$var wire 4 } _000_ [3:0] $end
$upscope $end
$upscope $end
$scope module counter_tb $end
$var reg 1 ! clk $end
$upscope $end
$enddefinitions $end
$comment Show the parameter values. $end
$dumpall
$end
#0
$dumpvars
bx }
x|
x{
xz
xy
xx
xw
xv
xu
xt
xs
xr
xq
xp
xo
xn
xm
xl
xk
xj
xi
xh
xg
xf
xe
xd
xc
xb
xa
x`
x_
x^
x]
x\
x[
xZ
xY
xX
xW
xV
xU
xT
xS
xR
xQ
xP
xO
xN
xM
xL
xK
xJ
xI
xH
xG
xF
xE
xD
xC
xB
xA
x@
x?
x>
x=
x<
x;
x:
x9
x8
x7
x6
x5
x4
x3
x2
x1
x0
x/
x.
x-
x,
x+
x*
x)
x(
x'
x&
x%
x$
bx #
0"
0!
$end
#1
1%
1&
1,
1/
18
19
1?
1B
1K
1L
1R
1U
1^
1_
1e
1h
#2
0$
03
04
0+
0.
07
0F
0G
0>
0A
0J
0Y
0Z
0Q
0T
0]
0l
0m
0d
0g
#3
10
11
1*
1-
1C
1D
1=
1@
1V
1W
1P
1S
1i
1j
1c
1f
#4
0)
0<
0O
0b
#5
1(
1;
1N
1a
#50
1!
#51
0h
0_
0U
0L
0B
09
0/
0&
#52
1g
1l
1m
1T
1Y
1Z
1A
1F
1G
1.
13
14
#53
0f
xi
xj
0S
xV
xW
0@
xC
xD
0-
x0
x1
#54
1_
1L
19
1&
#55
0l
0m
0Y
0Z
0F
0G
03
04
#56
1i
1j
1V
1W
1C
1D
10
11
#100
0!
#101
1h
1U
1B
1/
#102
0g
0T
0A
0.
#103
1f
1S
1@
1-
#150
1!
#151
0h
0_
0U
0L
0B
09
0/
0&
#152
1g
1l
1m
1T
1Y
1Z
1A
1F
1G
1.
13
14
#153
0f
xi
xj
0S
xV
xW
0@
xC
xD
0-
x0
x1
#154
1_
1L
19
1&
#155
0l
0m
0Y
0Z
0F
0G
03
04
#156
1i
1j
1V
1W
1C
1D
10
11
#200
0!
#201
1h
1U
1B
1/
#202
0g
0T
0A
0.
#203
1f
1S
1@
1-
#250
1!
#251
0h
0_
0U
0L
0B
09
0/
0&
#252
1g
1l
1m
1T
1Y
1Z
1A
1F
1G
1.
13
14
#253
0f
xi
xj
0S
xV
xW
0@
xC
xD
0-
x0
x1
#254
1_
1L
19
1&
#255
0l
0m
0Y
0Z
0F
0G
03
04
#256
1i
1j
1V
1W
1C
1D
10
11
#300
0!
#301
1h
1U
1B
1/
#302
0g
0T
0A
0.
#303
1f
1S
1@
1-
#350
1!
#351
0h
0_
0U
0L
0B
09
0/
0&
#352
1g
1l
1m
1T
1Y
1Z
1A
1F
1G
1.
13
14
#353
0f
xi
xj
0S
xV
xW
0@
xC
xD
0-
x0
x1
#354
1_
1L
19
1&
#355
0l
0m
0Y
0Z
0F
0G
03
04
#356
1i
1j
1V
1W
1C
1D
10
11
#400
0!
#401
1h
1U
1B
1/
#402
0g
0T
0A
0.
#403
1f
1S
1@
1-
#450
1!
#451
0h
0_
0U
0L
0B
09
0/
0&
#452
1g
1l
1m
1T
1Y
1Z
1A
1F
1G
1.
13
14
#453
0f
xi
xj
0S
xV
xW
0@
xC
xD
0-
x0
x1
#454
1_
1L
19
1&
#455
0l
0m
0Y
0Z
0F
0G
03
04
#456
1i
1j
1V
1W
1C
1D
10
11
#500
0!
1"
#501
1h
1U
1B
1/
0e
0^
0R
0K
0?
08
0,
0%
#502
0g
0T
0A
0.
1d
1n
1l
1]
1Q
1[
1Y
1J
1>
1H
1F
17
1+
15
13
1$
#503
1f
1S
1@
1-
0c
0k
xi
xj
0P
0X
xV
xW
0=
0E
xC
xD
0*
02
x0
x1
#504
1b
1j
1`
1O
1W
1M
1<
1D
1:
1)
11
1'
#505
0a
0i
0N
0V
0;
0C
0(
00
#506
1^
1o
1K
1\
18
1I
1%
16
#507
xn
0l
0]
x[
0Y
0J
xH
0F
07
x5
03
0$
b0 #
#508
bx1 }
1z
1p
1v
1|
1r
1{
xk
1i
xX
1V
xE
1C
x2
10
#509
0n
0x
0y
0u
0t
x`
xM
x:
x'
#510
1k
1w
1q
1s
#511
0`
b1 }
#512
1[
15
1H
#513
0X
02
0E
#514
1M
1'
1:
