OnlyNandYosysSynth/test/NAND.v
module NAND(
    input wire A,
    input wire B,
    output wire Y
);

assign #1 Y = ~(A&B);

endmodule

OnlyNandYosysSynth/output/synth_counter1bit.v
/* Generated by Yosys 0.9 (git sha1 1979e0b) */

(* top =  1  *)
(* src = "counter1bit.v:1" *)
module counter1bit(clk, rst, count);
  (* src = "counter1bit.v:7" *)
  wire _00_;
  (* src = "counter1bit.v:7|all2nand.v:18" *)
  wire _01_;
  (* src = "counter1bit.v:7|all2nand.v:21" *)
  wire _02_;
  (* src = "counter1bit.v:7|all2nand.v:24" *)
  wire _03_;
  (* src = "counter1bit.v:7|all2nand.v:24" *)
  wire _04_;
  (* src = "counter1bit.v:7|all2nand.v:22" *)
  wire _05_;
  (* src = "counter1bit.v:7|all2nand.v:15" *)
  wire _06_;
  (* src = "counter1bit.v:7|all2nand.v:16" *)
  wire _07_;
  (* src = "counter1bit.v:7|all2nand.v:26" *)
  wire _08_;
  (* src = "counter1bit.v:7|all2nand.v:26" *)
  wire _09_;
  (* src = "counter1bit.v:7|all2nand.v:26" *)
  wire _10_;
  (* src = "counter1bit.v:7|all2nand.v:26" *)
  wire _11_;
  (* src = "counter1bit.v:7|all2nand.v:27" *)
  wire _12_;
  (* src = "counter1bit.v:7|all2nand.v:27" *)
  wire _13_;
  (* src = "counter1bit.v:7|all2nand.v:27" *)
  wire _14_;
  (* src = "counter1bit.v:7|all2nand.v:27" *)
  wire _15_;
  (* src = "counter1bit.v:7|all2nand.v:17" *)
  wire _16_;
  (* src = "counter1bit.v:7|all2nand.v:24" *)
  wire _17_;
  (* src = "counter1bit.v:7|all2nand.v:25" *)
  wire _18_;
  (* src = "counter1bit.v:7|all2nand.v:25" *)
  wire _19_;
  (* src = "counter1bit.v:2" *)
  input clk;
  (* src = "counter1bit.v:4" *)
  output count;
  (* src = "counter1bit.v:3" *)
  input rst;
  (* module_not_derived = 32'd1 *)
  (* src = "all2nand.v:3" *)
  NAND _20_ (
    .A(count),
    .B(count),
    .Y(_00_)
  );
  (* module_not_derived = 32'd1 *)
  (* src = "counter1bit.v:7|all2nand.v:53|all2nand.v:3" *)
  NAND _21_ (
    .A(_05_),
    .B(_05_),
    .Y(_16_)
  );
  (* module_not_derived = 32'd1 *)
  (* src = "counter1bit.v:7|all2nand.v:39|all2nand.v:3" *)
  NAND _22_ (
    .A(_12_),
    .B(_12_),
    .Y(_13_)
  );
  (* module_not_derived = 32'd1 *)
  (* src = "counter1bit.v:7|all2nand.v:40|all2nand.v:3" *)
  NAND _23_ (
    .A(_13_),
    .B(_13_),
    .Y(_14_)
  );
  (* module_not_derived = 32'd1 *)
  (* src = "counter1bit.v:7|all2nand.v:41|all2nand.v:3" *)
  NAND _24_ (
    .A(_14_),
    .B(_14_),
    .Y(_15_)
  );
  (* module_not_derived = 32'd1 *)
  (* src = "counter1bit.v:7|all2nand.v:43|all2nand.v:3" *)
  NAND _25_ (
    .A(_18_),
    .B(_18_),
    .Y(_19_)
  );
  (* module_not_derived = 32'd1 *)
  (* src = "counter1bit.v:7|all2nand.v:47|all2nand.v:3" *)
  NAND _26_ (
    .A(_02_),
    .B(_02_),
    .Y(_05_)
  );
  (* module_not_derived = 32'd1 *)
  (* src = "counter1bit.v:7|all2nand.v:30|all2nand.v:3" *)
  NAND _27_ (
    .A(clk),
    .B(clk),
    .Y(_08_)
  );
  (* module_not_derived = 32'd1 *)
  (* src = "counter1bit.v:7|all2nand.v:31|all2nand.v:3" *)
  NAND _28_ (
    .A(_08_),
    .B(_08_),
    .Y(_09_)
  );
  (* module_not_derived = 32'd1 *)
  (* src = "counter1bit.v:7|all2nand.v:32|all2nand.v:3" *)
  NAND _29_ (
    .A(_09_),
    .B(_09_),
    .Y(_10_)
  );
  (* module_not_derived = 32'd1 *)
  (* src = "counter1bit.v:7|all2nand.v:34|all2nand.v:3" *)
  NAND _30_ (
    .A(_17_),
    .B(_17_),
    .Y(_03_)
  );
  (* module_not_derived = 32'd1 *)
  (* src = "counter1bit.v:7|all2nand.v:37|all2nand.v:3" *)
  NAND _31_ (
    .A(rst),
    .B(rst),
    .Y(_11_)
  );
  (* module_not_derived = 32'd1 *)
  (* src = "counter1bit.v:7|all2nand.v:38|all2nand.v:3" *)
  NAND _32_ (
    .A(_11_),
    .B(_11_),
    .Y(_12_)
  );
  (* module_not_derived = 32'd1 *)
  (* src = "counter1bit.v:7|all2nand.v:54" *)
  NAND _33_ (
    .A(_04_),
    .B(_05_),
    .Y(_06_)
  );
  (* module_not_derived = 32'd1 *)
  (* src = "counter1bit.v:7|all2nand.v:55" *)
  NAND _34_ (
    .A(_04_),
    .B(_16_),
    .Y(_07_)
  );
  (* module_not_derived = 32'd1 *)
  (* src = "counter1bit.v:7|all2nand.v:56" *)
  NAND _35_ (
    .A(_06_),
    .B(_01_),
    .Y(count)
  );
  (* module_not_derived = 32'd1 *)
  (* src = "counter1bit.v:7|all2nand.v:57" *)
  NAND _36_ (
    .A(_07_),
    .B(count),
    .Y(_01_)
  );
  (* module_not_derived = 32'd1 *)
  (* src = "counter1bit.v:7|all2nand.v:33" *)
  NAND _37_ (
    .A(_10_),
    .B(clk),
    .Y(_17_)
  );
  (* module_not_derived = 32'd1 *)
  (* src = "counter1bit.v:7|all2nand.v:42" *)
  NAND _38_ (
    .A(_15_),
    .B(rst),
    .Y(_18_)
  );
  (* module_not_derived = 32'd1 *)
  (* src = "counter1bit.v:7|all2nand.v:46" *)
  NAND _39_ (
    .A(_18_),
    .B(_00_),
    .Y(_02_)
  );
  (* module_not_derived = 32'd1 *)
  (* src = "counter1bit.v:7|all2nand.v:50" *)
  NAND _40_ (
    .A(_18_),
    .B(_17_),
    .Y(_04_)
  );
endmodule

OnlyNandYosysSynth/test/counter1bit_tb.v
//iverilog -o .\out\counter1bit_tb .\counter1bit_tb.v .\synth_counter1bit.v .\DFF_PP0.v .\NOT.v .\NAND.v
module counter1bit_tb;
    reg clk, reset;
    wire counter;

    counter1bit count(clk, reset, counter);
    
    initial begin
        clk=0;
        forever #50 clk=~clk;
    end

    initial begin
        $dumpfile("counter1bit.vcd");
        $dumpvars(1,count, clk);
        $display("start");
        reset = 0;
        #500
        reset=1;
        #500;
        reset=0;
        #5000;
        $display("finish");
        $finish;
    end
endmodule

OnlyNandYosysSynth/test/out/counter1bit.vcd
$date
	Fri Aug 25 12:13:29 2023
$end
$version
	Icarus Verilog
$end
$timescale
	1s
$end
$scope module counter1bit_tb $end
$scope module count $end
$var wire 1 ! clk $end
$var wire 1 " rst $end
$var wire 1 # count $end
$var wire 1 $ _19_ $end
$var wire 1 % _18_ $end
$var wire 1 & _17_ $end
$var wire 1 ' _16_ $end
$var wire 1 ( _15_ $end
$var wire 1 ) _14_ $end
$var wire 1 * _13_ $end
$var wire 1 + _12_ $end
$var wire 1 , _11_ $end
$var wire 1 - _10_ $end
$var wire 1 . _09_ $end
$var wire 1 / _08_ $end
$var wire 1 0 _07_ $end
$var wire 1 1 _06_ $end
$var wire 1 2 _05_ $end
$var wire 1 3 _04_ $end
$var wire 1 4 _03_ $end
$var wire 1 5 _02_ $end
$var wire 1 6 _01_ $end
$var wire 1 7 _00_ $end
$upscope $end
$upscope $end
$scope module counter1bit_tb $end
$var reg 1 ! clk $end
$upscope $end
$enddefinitions $end
$comment Show the parameter values. $end
$dumpall
$end
#0
$dumpvars
x7
x6
x5
x4
x3
x2
x1
x0
x/
x.
x-
x,
x+
x*
x)
x(
x'
x&
x%
x$
x#
0"
0!
$end
#1
1%
1&
1,
1/
#2
0$
03
04
0+
0.
#3
10
11
1*
1-
#4
0)
#5
1(
#50
1!
#51
0/
0&
#52
1.
13
14
#53
0-
x0
x1
#54
1&
#55
03
04
#56
10
11
#100
0!
#101
1/
#102
0.
#103
1-
#150
1!
#151
0/
0&
#152
1.
13
14
#153
0-
x0
x1
#154
1&
#155
03
04
#156
10
11
#200
0!
#201
1/
#202
0.
#203
1-
#250
1!
#251
0/
0&
#252
1.
13
14
#253
0-
x0
x1
#254
1&
#255
03
04
#256
10
11
#300
0!
#301
1/
#302
0.
#303
1-
#350
1!
#351
0/
0&
#352
1.
13
14
#353
0-
x0
x1
#354
1&
#355
03
04
#356
10
11
#400
0!
#401
1/
#402
0.
#403
1-
#450
1!
#451
0/
0&
#452
1.
13
14
#453
0-
x0
x1
#454
1&
#455
03
04
#456
10
11
#500
0!
1"
#501
1/
0,
0%
#502
0.
1+
15
13
1$
#503
1-
0*
02
x0
x1
#504
1)
11
1'
#505
0(
00
#506
1%
16
#507
x5
03
0$
0#
#508
x2
10
17
#509
x'
05
#510
12
#511
0'
#550
1!
#551
0/
0&
#552
1.
13
14
#553
0-
01
#554
1&
1#
#555
03
04
06
07
#556
11
15
#557
02
#558
1'
#600
0!
#601
1/
#602
0.
#603
1-
#650
1!
#651
0/
0&
#652
1.
13
14
#653
0-
00
#654
1&
16
#655
03
04
0#
#656
10
17
#657
05
#658
12
#659
0'
#700
0!
#701
1/
#702
0.
#703
1-
#750
1!
#751
0/
0&
#752
1.
13
14
#753
0-
01
#754
1&
1#
#755
03
04
06
07
#756
11
15
#757
02
#758
1'
#800
0!
#801
1/
#802
0.
#803
1-
#850
1!
#851
0/
0&
#852
1.
13
14
#853
0-
00
#854
1&
16
#855
03
04
0#
#856
10
17
#857
05
#858
12
#859
0'
#900
0!
#901
1/
#902
0.
#903
1-
#950
1!
#951
0/
0&
#952
1.
13
14
#953
0-
01
#954
1&
1#
#955
03
04
06
07
#956
11
15
#957
02
#958
1'
#1000
0!
0"
#1001
1/
1,
#1002
0.
0+
#1003
1-
1*
#1004
0)
#1005
1(
#1050
1!
#1051
0/
0&
#1052
1.
13
14
#1053
0-
00
#1054
1&
16
#1055
03
04
0#
#1056
10
17
#1057
05
#1058
12
#1059
0'
#1100
0!
#1101
1/
#1102
0.
#1103
1-
#1150
1!
#1151
0/
0&
#1152
1.
13
14
#1153
0-
01
#1154
1&
1#
#1155
03
04
06
07
#1156
11
15
#1157
02
#1158
1'
#1200
0!
#1201
1/
#1202
0.
#1203
1-
#1250
1!
#1251
0/
0&
#1252
1.
13
14
#1253
0-
00
#1254
1&
16
#1255
03
04
0#
#1256
10
17
#1257
05
#1258
12
#1259
0'
#1300
0!
#1301
1/
#1302
0.
#1303
1-
#1350
1!
#1351
0/
0&
#1352
1.
13
14
#1353
0-
01
#1354
1&
1#
#1355
03
04
06
07
#1356
11
15
#1357
02
#1358
1'
#1400
0!
#1401
1/
#1402
0.
#1403
1-
#1450
1!
#1451
0/
0&
#1452
1.
13
14
#1453
0-
00
#1454
1&
16
#1455
03
04
0#
#1456
10
17
#1457
05
#1458
12
#1459
0'
#1500
0!
#1501
1/
#1502
0.
#1503
1-
#1550
1!
#1551
0/
0&
#1552
1.
13
14
#1553
0-
01
#1554
1&
1#
#1555
03
04
06
07
#1556
11
15
#1557
02
#1558
1'
#1600
0!
#1601
1/
#1602
0.
#1603
1-
#1650
1!
#1651
0/
0&
#1652
1.
13
14
#1653
0-
00
#1654
1&
16
#1655
03
04
0#
#1656
10
17
#1657
05
#1658
12
#1659
0'
#1700
0!
#1701
1/
#1702
0.
#1703
1-
#1750
1!
#1751
0/
0&
#1752
1.
13
14
#1753
0-
01
#1754
1&
1#
#1755
03
04
06
07
#1756
11
15
#1757
02
#1758
1'
#1800
0!
#1801
1/
#1802
0.
#1803
1-
#1850
1!
#1851
0/
0&
#1852
1.
13
14
#1853
0-
00
#1854
1&
16
#1855
03
04
0#
#1856
10
17
#1857
05
#1858
12
#1859
0'
#1900
0!
#1901
1/
#1902
0.
#1903
1-
#1950
1!
#1951
0/
0&
#1952
1.
13
14
#1953
0-
01
#1954
1&
1#
#1955
03
04
06
07
#1956
11
15
#1957
02
#1958
1'
#2000
0!
#2001
1/
#2002
0.
#2003
1-
#2050
1!
#2051
0/
0&
#2052
1.
13
14
#2053
0-
00
#2054
1&
16
#2055
03
04
0#
#2056
10
17
#2057
05
#2058
12
#2059
0'
#2100
0!
#2101
1/
#2102
0.
#2103
1-
#2150
1!
#2151
0/
0&
#2152
1.
13
14
#2153
0-
01
#2154
1&
1#
#2155
03
04
06
07
#2156
11
15
#2157
02
#2158
1'
#2200
0!
#2201
1/
#2202
0.
#2203
1-
#2250
1!
#2251
0/
0&
#2252
1.
13
14
#2253
0-
00
#2254
1&
16
#2255
03
04
0#
#2256
10
17
#2257
05
#2258
12
#2259
0'
#2300
0!
#2301
1/
#2302
0.
#2303
1-
#2350
1!
#2351
0/
0&
#2352
1.
13
14
#2353
0-
01
#2354
1&
1#
#2355
03
04
06
07
#2356
11
15
#2357
02
#2358
1'
#2400
0!
#2401
1/
#2402
0.
#2403
1-
#2450
1!
#2451
0/
0&
#2452
1.
13
14
#2453
0-
00
#2454
1&
16
#2455
03
04
0#
#2456
10
17
#2457
05
#2458
12
#2459
0'
#2500
0!
#2501
1/
#2502
0.
#2503
1-
#2550
1!
#2551
0/
0&
#2552
1.
13
14
#2553
0-
01
#2554
1&
1#
#2555
03
04
06
07
#2556
11
15
#2557
02
#2558
1'
#2600
0!
#2601
1/
#2602
0.
#2603
1-
#2650
1!
#2651
0/
0&
#2652
1.
13
14
#2653
0-
00
#2654
1&
16
#2655
03
04
0#
#2656
10
17
#2657
05
#2658
12
#2659
0'
#2700
0!
#2701
1/
#2702
0.
#2703
1-
#2750
1!
#2751
0/
0&
#2752
1.
13
14
#2753
0-
01
#2754
1&
1#
#2755
03
04
06
07
#2756
11
15
#2757
02
#2758
1'
#2800
0!
#2801
1/
#2802
0.
#2803
1-
#2850
1!
#2851
0/
0&
#2852
1.
13
14
#2853
0-
00
#2854
1&
16
#2855
03
04
0#
#2856
10
17
#2857
05
#2858
12
#2859
0'
#2900
0!
#2901
1/
#2902
0.
#2903
1-
#2950
1!
#2951
0/
0&
#2952
1.
13
14
#2953
0-
01
#2954
1&
1#
#2955
03
04
06
07
#2956
11
15
#2957
02
#2958
1'
#3000
0!
#3001
1/
#3002
0.
#3003
1-
#3050
1!
#3051
0/
0&
#3052
1.
13
14
#3053
0-
00
#3054
1&
16
#3055
03
04
0#
#3056
10
17
#3057
05
#3058
12
#3059
0'
#3100
0!
#3101
1/
#3102
0.
#3103
1-
#3150
1!
#3151
0/
0&
#3152
1.
13
14
#3153
0-
01
#3154
1&
1#
#3155
03
04
06
07
#3156
11
15
#3157
02
#3158
1'
#3200
0!
#3201
1/
#3202
0.
#3203
1-
#3250
1!
#3251
0/
0&
#3252
1.
13
14
#3253
0-
00
#3254
1&
16
#3255
03
04
0#
#3256
10
17
#3257
05
#3258
12
#3259
0'
#3300
0!
#3301
1/
#3302
0.
#3303
1-
#3350
1!
#3351
0/
0&
#3352
1.
13
14
#3353
0-
01
#3354
1&
1#
#3355
03
04
06
07
#3356
11
15
#3357
02
#3358
1'
#3400
0!
#3401
1/
#3402
0.
#3403
1-
#3450
1!
#3451
0/
0&
#3452
1.
13
14
#3453
0-
00
#3454
1&
16
#3455
03
04
0#
#3456
10
17
#3457
05
#3458
12
#3459
0'
#3500
0!
#3501
1/
#3502
0.
#3503
1-
#3550
1!
#3551
0/
0&
#3552
1.
13
14
#3553
0-
01
#3554
1&
1#
#3555
03
04
06
07
#3556
11
15
#3557
02
#3558
1'
#3600
0!
#3601
1/
#3602
0.
#3603
1-
#3650
1!
#3651
0/
0&
#3652
1.
13
14
#3653
0-
00
#3654
1&
16
#3655
03
04
0#
#3656
10
17
#3657
05
#3658
12
#3659
0'
#3700
0!
#3701
1/
#3702
0.
#3703
1-
#3750
1!
#3751
0/
0&
#3752
1.
13
14
#3753
0-
01
#3754
1&
1#
#3755
03
04
06
07
#3756
11
15
#3757
02
#3758
1'
#3800
0!
#3801
1/
#3802
0.
#3803
1-
#3850
1!
#3851
0/
0&
#3852
1.
13
14
#3853
0-
00
#3854
1&
16
#3855
03
04
0#
#3856
10
17
#3857
05
#3858
12
#3859
0'
#3900
0!
#3901
1/
#3902
0.
#3903
1-
#3950
1!
#3951
0/
0&
#3952
1.
13
14
#3953
0-
01
#3954
1&
1#
#3955
03
04
06
07
#3956
11
15
#3957
02
#3958
1'
#4000
0!
#4001
1/
#4002
0.
#4003
1-
#4050
1!
#4051
0/
0&
#4052
1.
13
14
#4053
0-
00
#4054
1&
16
#4055
03
04
0#
#4056
10
17
#4057
05
#4058
12
#4059
0'
#4100
0!
#4101
1/
#4102
0.
#4103
1-
#4150
1!
#4151
0/
0&
#4152
1.
13
14
#4153
0-
01
#4154
1&
1#
#4155
03
04
06
07
#4156
11
15
#4157
02
#4158
1'
#4200
0!
#4201
1/
#4202
0.
#4203
1-
#4250
1!
#4251
0/
0&
#4252
1.
13
14
#4253
0-
00
#4254
1&
16
#4255
03
04
0#
#4256
10
17
#4257
05
#4258
12
#4259
0'
#4300
0!
#4301
1/
#4302
0.
#4303
1-
#4350
1!
#4351
0/
0&
#4352
1.
13
14
#4353
0-
01
#4354
1&
1#
#4355
03
04
06
07
#4356
11
15
#4357
02
#4358
1'
#4400
0!
#4401
1/
#4402
0.
#4403
1-
#4450
1!
#4451
0/
0&
#4452
1.
13
14
#4453
0-
00
#4454
1&
16
#4455
03
04
0#
#4456
10
17
#4457
05
#4458
12
#4459
0'
#4500
0!
#4501
1/
#4502
0.
#4503
1-
#4550
1!
#4551
0/
0&
#4552
1.
13
14
#4553
0-
01
#4554
1&
1#
#4555
03
04
06
07
#4556
11
15
#4557
02
#4558
1'
#4600
0!
#4601
1/
#4602
0.
#4603
1-
#4650
1!
#4651
0/
0&
#4652
1.
13
14
#4653
0-
00
#4654
1&
16
#4655
03
04
0#
#4656
10
17
#4657
05
#4658
12
#4659
0'
#4700
0!
#4701
1/
#4702
0.
#4703
1-
#4750
1!
#4751
0/
0&
#4752
1.
13
14
#4753
0-
01
#4754
1&
1#
#4755
03
04
06
07
#4756
11
15
#4757
02
#4758
1'
#4800
0!
#4801
1/
#4802
0.
#4803
1-
#4850
1!
#4851
0/
0&
#4852
1.
13
14
#4853
0-
00
#4854
1&
16
#4855
03
04
0#
#4856
10
17
#4857
05
#4858
12
#4859
0'
#4900
0!
#4901
1/
#4902
0.
#4903
1-
#4950
1!
#4951
0/
0&
#4952
1.
13
14
#4953
0-
01
#4954
1&
1#
#4955
03
04
06
07
#4956
11
15
#4957
02
#4958
1'
#5000
0!
#5001
1/
#5002
0.
#5003
1-
#5050
1!
#5051
0/
0&
#5052
1.
13
14
#5053
0-
00
#5054
1&
16
#5055
03
04
0#
#5056
10
17
#5057
05
#5058
12
#5059
0'
#5100
0!
#5101
1/
#5102
0.
#5103
1-
#5150
1!
#5151
0/
0&
#5152
1.
13
14
#5153
0-
01
#5154
1&
1#
#5155
03
04
06
07
#5156
11
15
#5157
02
#5158
1'
#5200
0!
#5201
1/
#5202
0.
#5203
1-
#5250
1!
#5251
0/
0&
#5252
1.
13
14
#5253
0-
00
#5254
1&
16
#5255
03
04
0#
#5256
10
17
#5257
05
#5258
12
#5259
0'
#5300
0!
#5301
1/
#5302
0.
#5303
1-
#5350
1!
#5351
0/
0&
#5352
1.
13
14
#5353
0-
01
#5354
1&
1#
#5355
03
04
06
07
#5356
11
15
#5357
02
#5358
1'
#5400
0!
#5401
1/
#5402
0.
#5403
1-
#5450
1!
#5451
0/
0&
#5452
1.
13
14
#5453
0-
00
#5454
1&
16
#5455
03
04
0#
#5456
10
17
#5457
05
#5458
12
#5459
0'
#5500
0!
#5501
1/
#5502
0.
#5503
1-
#5550
1!
#5551
0/
0&
#5552
1.
13
14
#5553
0-
01
#5554
1&
1#
#5555
03
04
06
07
#5556
11
15
#5557
02
#5558
1'
#5600
0!
#5601
1/
#5602
0.
#5603
1-
#5650
1!
#5651
0/
0&
#5652
1.
13
14
#5653
0-
00
#5654
1&
16
#5655
03
04
0#
#5656
10
17
#5657
05
#5658
12
#5659
0'
#5700
0!
#5701
1/
#5702
0.
#5703
1-
#5750
1!
#5751
0/
0&
#5752
1.
13
14
#5753
0-
01
#5754
1&
1#
#5755
03
04
06
07
#5756
11
15
#5757
02
#5758
1'
#5800
0!
#5801
1/
#5802
0.
#5803
1-
#5850
1!
#5851
0/
0&
#5852
1.
13
14
#5853
0-
00
#5854
1&
16
#5855
03
04
0#
#5856
10
17
#5857
05
#5858
12
#5859
0'
#5900
0!
#5901
1/
#5902
0.
#5903
1-
#5950
1!
#5951
0/
0&
#5952
1.
13
14
#5953
0-
01
#5954
1&
1#
#5955
03
04
06
07
#5956
11
15
#5957
02
#5958
1'
