OnlyNandYosysSynth/test/NAND.v
module NAND(
    input wire A,
    input wire B,
    output wire Y
);

assign #1 Y = ~(A&B);

endmodule

OnlyNandYosysSynth/output/synth_counter.v
/* Generated by Yosys 0.9 (git sha1 1979e0b) */

(* top =  1  *)
(* src = "counter.v:1" *)
module counter(clk, rst, count);
  (* src = "counter.v:7" *)
  wire [3:0] _000_;
  wire _001_;
  wire _002_;
  wire _003_;
  wire _004_;
  wire _005_;
  wire _006_;
  wire _007_;
  wire _008_;
  wire _009_;
  wire _010_;
  wire _011_;
  wire _012_;
  wire _013_;
  (* src = "counter.v:7|all2nand.v:18" *)
  wire _014_;
  (* src = "counter.v:7|all2nand.v:17" *)
  wire _015_;
  (* src = "counter.v:7|all2nand.v:19" *)
  wire _016_;
  (* src = "counter.v:7|all2nand.v:20" *)
  wire _017_;
  (* src = "counter.v:7|all2nand.v:21" *)
  wire _018_;
  (* src = "counter.v:7|all2nand.v:24" *)
  wire _019_;
  (* src = "counter.v:7|all2nand.v:22" *)
  wire _020_;
  (* src = "counter.v:7|all2nand.v:23" *)
  wire _021_;
  (* src = "counter.v:7|all2nand.v:15" *)
  wire _022_;
  (* src = "counter.v:7|all2nand.v:18" *)
  wire _023_;
  (* src = "counter.v:7|all2nand.v:17" *)
  wire _024_;
  (* src = "counter.v:7|all2nand.v:19" *)
  wire _025_;
  (* src = "counter.v:7|all2nand.v:20" *)
  wire _026_;
  (* src = "counter.v:7|all2nand.v:21" *)
  wire _027_;
  (* src = "counter.v:7|all2nand.v:24" *)
  wire _028_;
  (* src = "counter.v:7|all2nand.v:22" *)
  wire _029_;
  (* src = "counter.v:7|all2nand.v:23" *)
  wire _030_;
  (* src = "counter.v:7|all2nand.v:15" *)
  wire _031_;
  (* src = "counter.v:7|all2nand.v:18" *)
  wire _032_;
  (* src = "counter.v:7|all2nand.v:17" *)
  wire _033_;
  (* src = "counter.v:7|all2nand.v:19" *)
  wire _034_;
  (* src = "counter.v:7|all2nand.v:20" *)
  wire _035_;
  (* src = "counter.v:7|all2nand.v:21" *)
  wire _036_;
  (* src = "counter.v:7|all2nand.v:24" *)
  wire _037_;
  (* src = "counter.v:7|all2nand.v:22" *)
  wire _038_;
  (* src = "counter.v:7|all2nand.v:23" *)
  wire _039_;
  (* src = "counter.v:7|all2nand.v:15" *)
  wire _040_;
  (* src = "counter.v:7|all2nand.v:18" *)
  wire _041_;
  (* src = "counter.v:7|all2nand.v:17" *)
  wire _042_;
  (* src = "counter.v:7|all2nand.v:19" *)
  wire _043_;
  (* src = "counter.v:7|all2nand.v:20" *)
  wire _044_;
  (* src = "counter.v:7|all2nand.v:21" *)
  wire _045_;
  (* src = "counter.v:7|all2nand.v:24" *)
  wire _046_;
  (* src = "counter.v:7|all2nand.v:22" *)
  wire _047_;
  (* src = "counter.v:7|all2nand.v:23" *)
  wire _048_;
  (* src = "counter.v:7|all2nand.v:15" *)
  wire _049_;
  (* src = "counter.v:2" *)
  input clk;
  (* src = "counter.v:4" *)
  output [3:0] count;
  (* src = "counter.v:3" *)
  input rst;
  (* module_not_derived = 32'd1 *)
  (* src = "all2nand.v:3" *)
  NAND _050_ (
    .A(count[1]),
    .B(count[1]),
    .Y(_013_)
  );
  (* module_not_derived = 32'd1 *)
  (* src = "all2nand.v:3" *)
  NAND _051_ (
    .A(count[0]),
    .B(count[0]),
    .Y(_000_[0])
  );
  (* module_not_derived = 32'd1 *)
  (* src = "all2nand.v:3" *)
  NAND _052_ (
    .A(count[2]),
    .B(count[2]),
    .Y(_001_)
  );
  (* module_not_derived = 32'd1 *)
  (* src = "all2nand.v:3" *)
  NAND _053_ (
    .A(count[3]),
    .B(count[3]),
    .Y(_002_)
  );
  NAND _054_ (
    .A(count[1]),
    .B(count[0]),
    .Y(_003_)
  );
  (* module_not_derived = 32'd1 *)
  (* src = "all2nand.v:3" *)
  NAND _055_ (
    .A(_003_),
    .B(_003_),
    .Y(_004_)
  );
  NAND _056_ (
    .A(_013_),
    .B(_000_[0]),
    .Y(_005_)
  );
  NAND _057_ (
    .A(_003_),
    .B(_005_),
    .Y(_006_)
  );
  (* module_not_derived = 32'd1 *)
  (* src = "all2nand.v:3" *)
  NAND _058_ (
    .A(_006_),
    .B(_006_),
    .Y(_000_[1])
  );
  NAND _059_ (
    .A(count[2]),
    .B(_004_),
    .Y(_007_)
  );
  (* module_not_derived = 32'd1 *)
  (* src = "all2nand.v:3" *)
  NAND _060_ (
    .A(_007_),
    .B(_007_),
    .Y(_008_)
  );
  NAND _061_ (
    .A(_001_),
    .B(_003_),
    .Y(_009_)
  );
  NAND _062_ (
    .A(_007_),
    .B(_009_),
    .Y(_010_)
  );
  (* module_not_derived = 32'd1 *)
  (* src = "all2nand.v:3" *)
  NAND _063_ (
    .A(_010_),
    .B(_010_),
    .Y(_000_[2])
  );
  NAND _064_ (
    .A(count[3]),
    .B(_007_),
    .Y(_011_)
  );
  NAND _065_ (
    .A(_002_),
    .B(_008_),
    .Y(_012_)
  );
  NAND _066_ (
    .A(_011_),
    .B(_012_),
    .Y(_000_[3])
  );
  (* module_not_derived = 32'd1 *)
  (* src = "counter.v:7|all2nand.v:26|all2nand.v:3" *)
  NAND _067_ (
    .A(rst),
    .B(rst),
    .Y(_022_)
  );
  (* module_not_derived = 32'd1 *)
  (* src = "counter.v:7|all2nand.v:27" *)
  NAND _068_ (
    .A(_022_),
    .B(clk),
    .Y(_014_)
  );
  (* module_not_derived = 32'd1 *)
  (* src = "counter.v:7|all2nand.v:28" *)
  NAND _069_ (
    .A(_000_[0]),
    .B(_020_),
    .Y(_015_)
  );
  (* module_not_derived = 32'd1 *)
  (* src = "counter.v:7|all2nand.v:29" *)
  NAND _070_ (
    .A(_015_),
    .B(_021_),
    .Y(_016_)
  );
  (* module_not_derived = 32'd1 *)
  (* src = "counter.v:7|all2nand.v:30" *)
  NAND _071_ (
    .A(_016_),
    .B(_022_),
    .Y(_017_)
  );
  (* module_not_derived = 32'd1 *)
  (* src = "counter.v:7|all2nand.v:31" *)
  NAND _072_ (
    .A(_017_),
    .B(_017_),
    .Y(_018_)
  );
  (* module_not_derived = 32'd1 *)
  (* src = "counter.v:7|all2nand.v:32" *)
  NAND _073_ (
    .A(_017_),
    .B(_014_),
    .Y(_020_)
  );
  (* module_not_derived = 32'd1 *)
  (* src = "counter.v:7|all2nand.v:33" *)
  NAND _074_ (
    .A(_018_),
    .B(_014_),
    .Y(_021_)
  );
  (* module_not_derived = 32'd1 *)
  (* src = "counter.v:7|all2nand.v:34" *)
  NAND _075_ (
    .A(_020_),
    .B(count[0]),
    .Y(_019_)
  );
  (* module_not_derived = 32'd1 *)
  (* src = "counter.v:7|all2nand.v:35" *)
  NAND _076_ (
    .A(_021_),
    .B(_019_),
    .Y(count[0])
  );
  (* module_not_derived = 32'd1 *)
  (* src = "counter.v:7|all2nand.v:26|all2nand.v:3" *)
  NAND _077_ (
    .A(rst),
    .B(rst),
    .Y(_031_)
  );
  (* module_not_derived = 32'd1 *)
  (* src = "counter.v:7|all2nand.v:27" *)
  NAND _078_ (
    .A(_031_),
    .B(clk),
    .Y(_023_)
  );
  (* module_not_derived = 32'd1 *)
  (* src = "counter.v:7|all2nand.v:28" *)
  NAND _079_ (
    .A(_000_[1]),
    .B(_029_),
    .Y(_024_)
  );
  (* module_not_derived = 32'd1 *)
  (* src = "counter.v:7|all2nand.v:29" *)
  NAND _080_ (
    .A(_024_),
    .B(_030_),
    .Y(_025_)
  );
  (* module_not_derived = 32'd1 *)
  (* src = "counter.v:7|all2nand.v:30" *)
  NAND _081_ (
    .A(_025_),
    .B(_031_),
    .Y(_026_)
  );
  (* module_not_derived = 32'd1 *)
  (* src = "counter.v:7|all2nand.v:31" *)
  NAND _082_ (
    .A(_026_),
    .B(_026_),
    .Y(_027_)
  );
  (* module_not_derived = 32'd1 *)
  (* src = "counter.v:7|all2nand.v:32" *)
  NAND _083_ (
    .A(_026_),
    .B(_023_),
    .Y(_029_)
  );
  (* module_not_derived = 32'd1 *)
  (* src = "counter.v:7|all2nand.v:33" *)
  NAND _084_ (
    .A(_027_),
    .B(_023_),
    .Y(_030_)
  );
  (* module_not_derived = 32'd1 *)
  (* src = "counter.v:7|all2nand.v:34" *)
  NAND _085_ (
    .A(_029_),
    .B(count[1]),
    .Y(_028_)
  );
  (* module_not_derived = 32'd1 *)
  (* src = "counter.v:7|all2nand.v:35" *)
  NAND _086_ (
    .A(_030_),
    .B(_028_),
    .Y(count[1])
  );
  (* module_not_derived = 32'd1 *)
  (* src = "counter.v:7|all2nand.v:26|all2nand.v:3" *)
  NAND _087_ (
    .A(rst),
    .B(rst),
    .Y(_040_)
  );
  (* module_not_derived = 32'd1 *)
  (* src = "counter.v:7|all2nand.v:27" *)
  NAND _088_ (
    .A(_040_),
    .B(clk),
    .Y(_032_)
  );
  (* module_not_derived = 32'd1 *)
  (* src = "counter.v:7|all2nand.v:28" *)
  NAND _089_ (
    .A(_000_[2]),
    .B(_038_),
    .Y(_033_)
  );
  (* module_not_derived = 32'd1 *)
  (* src = "counter.v:7|all2nand.v:29" *)
  NAND _090_ (
    .A(_033_),
    .B(_039_),
    .Y(_034_)
  );
  (* module_not_derived = 32'd1 *)
  (* src = "counter.v:7|all2nand.v:30" *)
  NAND _091_ (
    .A(_034_),
    .B(_040_),
    .Y(_035_)
  );
  (* module_not_derived = 32'd1 *)
  (* src = "counter.v:7|all2nand.v:31" *)
  NAND _092_ (
    .A(_035_),
    .B(_035_),
    .Y(_036_)
  );
  (* module_not_derived = 32'd1 *)
  (* src = "counter.v:7|all2nand.v:32" *)
  NAND _093_ (
    .A(_035_),
    .B(_032_),
    .Y(_038_)
  );
  (* module_not_derived = 32'd1 *)
  (* src = "counter.v:7|all2nand.v:33" *)
  NAND _094_ (
    .A(_036_),
    .B(_032_),
    .Y(_039_)
  );
  (* module_not_derived = 32'd1 *)
  (* src = "counter.v:7|all2nand.v:34" *)
  NAND _095_ (
    .A(_038_),
    .B(count[2]),
    .Y(_037_)
  );
  (* module_not_derived = 32'd1 *)
  (* src = "counter.v:7|all2nand.v:35" *)
  NAND _096_ (
    .A(_039_),
    .B(_037_),
    .Y(count[2])
  );
  (* module_not_derived = 32'd1 *)
  (* src = "counter.v:7|all2nand.v:26|all2nand.v:3" *)
  NAND _097_ (
    .A(rst),
    .B(rst),
    .Y(_049_)
  );
  (* module_not_derived = 32'd1 *)
  (* src = "counter.v:7|all2nand.v:27" *)
  NAND _098_ (
    .A(_049_),
    .B(clk),
    .Y(_041_)
  );
  (* module_not_derived = 32'd1 *)
  (* src = "counter.v:7|all2nand.v:28" *)
  NAND _099_ (
    .A(_000_[3]),
    .B(_047_),
    .Y(_042_)
  );
  (* module_not_derived = 32'd1 *)
  (* src = "counter.v:7|all2nand.v:29" *)
  NAND _100_ (
    .A(_042_),
    .B(_048_),
    .Y(_043_)
  );
  (* module_not_derived = 32'd1 *)
  (* src = "counter.v:7|all2nand.v:30" *)
  NAND _101_ (
    .A(_043_),
    .B(_049_),
    .Y(_044_)
  );
  (* module_not_derived = 32'd1 *)
  (* src = "counter.v:7|all2nand.v:31" *)
  NAND _102_ (
    .A(_044_),
    .B(_044_),
    .Y(_045_)
  );
  (* module_not_derived = 32'd1 *)
  (* src = "counter.v:7|all2nand.v:32" *)
  NAND _103_ (
    .A(_044_),
    .B(_041_),
    .Y(_047_)
  );
  (* module_not_derived = 32'd1 *)
  (* src = "counter.v:7|all2nand.v:33" *)
  NAND _104_ (
    .A(_045_),
    .B(_041_),
    .Y(_048_)
  );
  (* module_not_derived = 32'd1 *)
  (* src = "counter.v:7|all2nand.v:34" *)
  NAND _105_ (
    .A(_047_),
    .B(count[3]),
    .Y(_046_)
  );
  (* module_not_derived = 32'd1 *)
  (* src = "counter.v:7|all2nand.v:35" *)
  NAND _106_ (
    .A(_048_),
    .B(_046_),
    .Y(count[3])
  );
endmodule

OnlyNandYosysSynth/test/counter_tb.v
//iverilog -o .\out\counter_tb .\counter_tb.v .\synth_counter.v .\DFF_PP0.v .\NOT.v .\NAND.v
module counter_tb;
    reg clk, reset;
    wire [3:0] counter;

    counter count(clk, reset, counter);
    
    initial begin
        clk=0;
        forever #50 clk=~clk;
    end

    initial begin
        $dumpfile("counter.vcd");
        $dumpvars(1,count, clk);
        $display("start");
        reset = 0;
        #500
        reset=1;
        #500;
        reset=0;
        #5000;
        $display("finish");
        $finish;
    end
endmodule

OnlyNandYosysSynth/test/out/counter.vcd
$date
	Tue Aug 29 16:17:34 2023
$end
$version
	Icarus Verilog
$end
$timescale
	1s
$end
$scope module counter_tb $end
$scope module count $end
$var wire 1 ! clk $end
$var wire 1 " rst $end
$var wire 4 # count [3:0] $end
$var wire 1 $ _049_ $end
$var wire 1 % _048_ $end
$var wire 1 & _047_ $end
$var wire 1 ' _046_ $end
$var wire 1 ( _045_ $end
$var wire 1 ) _044_ $end
$var wire 1 * _043_ $end
$var wire 1 + _042_ $end
$var wire 1 , _041_ $end
$var wire 1 - _040_ $end
$var wire 1 . _039_ $end
$var wire 1 / _038_ $end
$var wire 1 0 _037_ $end
$var wire 1 1 _036_ $end
$var wire 1 2 _035_ $end
$var wire 1 3 _034_ $end
$var wire 1 4 _033_ $end
$var wire 1 5 _032_ $end
$var wire 1 6 _031_ $end
$var wire 1 7 _030_ $end
$var wire 1 8 _029_ $end
$var wire 1 9 _028_ $end
$var wire 1 : _027_ $end
$var wire 1 ; _026_ $end
$var wire 1 < _025_ $end
$var wire 1 = _024_ $end
$var wire 1 > _023_ $end
$var wire 1 ? _022_ $end
$var wire 1 @ _021_ $end
$var wire 1 A _020_ $end
$var wire 1 B _019_ $end
$var wire 1 C _018_ $end
$var wire 1 D _017_ $end
$var wire 1 E _016_ $end
$var wire 1 F _015_ $end
$var wire 1 G _014_ $end
$var wire 1 H _013_ $end
$var wire 1 I _012_ $end
$var wire 1 J _011_ $end
$var wire 1 K _010_ $end
$var wire 1 L _009_ $end
$var wire 1 M _008_ $end
$var wire 1 N _007_ $end
$var wire 1 O _006_ $end
$var wire 1 P _005_ $end
$var wire 1 Q _004_ $end
$var wire 1 R _003_ $end
$var wire 1 S _002_ $end
$var wire 1 T _001_ $end
$var wire 4 U _000_ [3:0] $end
$upscope $end
$upscope $end
$scope module counter_tb $end
$var reg 1 ! clk $end
$upscope $end
$enddefinitions $end
$comment Show the parameter values. $end
$dumpall
$end
#0
$dumpvars
bx U
xT
xS
xR
xQ
xP
xO
xN
xM
xL
xK
xJ
xI
xH
xG
xF
xE
xD
xC
xB
xA
x@
x?
x>
x=
x<
x;
x:
x9
x8
x7
x6
x5
x4
x3
x2
x1
x0
x/
x.
x-
x,
x+
x*
x)
x(
x'
x&
x%
x$
bx #
0"
0!
$end
#1
1,
1$
15
1-
1>
16
1G
1?
#50
1!
#51
0G
0>
05
0,
#52
1A
1@
18
17
1/
1.
1&
1%
#100
0!
#101
1G
1>
15
1,
#102
xA
x@
x8
x7
x/
x.
x&
x%
#150
1!
#151
0G
0>
05
0,
#152
1A
1@
18
17
1/
1.
1&
1%
#200
0!
#201
1G
1>
15
1,
#202
xA
x@
x8
x7
x/
x.
x&
x%
#250
1!
#251
0G
0>
05
0,
#252
1A
1@
18
17
1/
1.
1&
1%
#300
0!
#301
1G
1>
15
1,
#302
xA
x@
x8
x7
x/
x.
x&
x%
#350
1!
#351
0G
0>
05
0,
#352
1A
1@
18
17
1/
1.
1&
1%
#400
0!
#401
1G
1>
15
1,
#402
xA
x@
x8
x7
x/
x.
x&
x%
#450
1!
#451
0G
0>
05
0,
#452
1A
1@
18
17
1/
1.
1&
1%
#500
0!
1"
#501
1G
1>
15
1,
0?
06
0-
0$
#502
xA
x@
x8
x7
x/
x.
x&
x%
1D
1;
12
1)
#503
0C
0A
0:
08
01
0/
0(
0&
#504
1@
1B
1F
17
19
1=
1.
10
14
1%
1'
1+
#505
0E
0<
03
b0 #
0*
#506
bx1 U
1R
1H
1N
1T
1J
1S
#507
0P
0Q
0M
0L
#508
1O
1I
1K
#509
b1 U
#550
1!
#600
0!
#650
1!
#700
0!
#750
1!
#800
0!
#850
1!
#900
0!
#950
1!
#1000
0!
0"
#1001
1?
16
1-
1$
#1050
1!
#1051
0G
0>
05
0,
#1052
1A
18
1/
1&
#1053
0F
#1054
1E
#1055
0D
#1056
1C
#1100
0!
#1101
1G
1>
15
1,
#1102
0@
08
0/
0&
#1103
b1 #
#1104
0B
b0 U
#1105
1F
1P
#1106
0O
#1107
b10 U
#1150
1!
#1151
0G
0>
05
0,
#1152
1@
18
1/
1&
#1153
0E
0=
#1154
1D
1<
#1155
0C
0;
#1156
1:
#1200
0!
#1201
1G
1>
15
1,
#1202
0A
07
0/
0&
#1203
1B
b11 #
#1204
09
0R
0H
b10 #
#1205
1R
b11 U
1Q
1O
1L
#1206
0Q
0O
0L
b1 U
0K
#1207
1=
1K
b111 U
#1208
0=
b11 U
#1250
1!
#1251
0G
0>
05
0,
#1252
1A
17
1/
1&
#1253
0F
#1254
1E
#1255
0D
#1256
1C
#1300
0!
#1301
1G
1>
15
1,
#1302
0@
07
0/
0&
#1303
b11 #
#1304
0B
0R
b10 U
#1305
1F
1Q
1O
1L
#1306
b0 U
0K
#1307
1=
b100 U
#1350
1!
#1351
0G
0>
05
0,
#1352
1@
17
1/
1&
#1353
0E
0<
04
#1354
1D
1;
13
#1355
0C
0:
02
#1356
11
#1400
0!
#1401
1G
1>
15
1,
#1402
0A
08
0.
0&
#1403
1B
19
b111 #
#1404
00
0N
0T
b100 #
#1405
b101 U
1R
1H
1M
1K
#1406
0P
0Q
0O
0I
b1 U
#1407
14
1O
1N
b1011 U
#1408
b1001 U
0M
0K
#1409
1I
b1101 U
#1410
04
b101 U
#1450
1!
#1451
0G
0>
05
0,
#1452
1A
18
1.
1&
#1453
0F
#1454
1E
#1455
0D
#1456
1C
#1500
0!
#1501
1G
1>
15
1,
#1502
0@
08
0.
0&
#1503
b101 #
#1504
0B
b100 U
#1505
1F
1P
#1506
0O
#1507
b110 U
#1550
1!
#1551
0G
0>
05
0,
#1552
1@
18
1.
1&
#1553
0E
0=
#1554
1D
1<
#1555
0C
0;
#1556
1:
#1600
0!
#1601
1G
1>
15
1,
#1602
0A
07
0.
0&
#1603
1B
b111 #
#1604
09
0R
0H
b110 #
#1605
1R
b111 U
1Q
1O
#1606
0Q
0O
0N
b101 U
#1607
1=
1N
b111 U
1M
1K
#1608
0=
0M
0K
0I
b11 U
#1609
14
1I
b1111 U
#1610
04
b111 U
#1650
1!
#1651
0G
0>
05
0,
#1652
1A
17
1.
1&
#1653
0F
#1654
1E
#1655
0D
#1656
1C
#1700
0!
#1701
1G
1>
15
1,
#1702
0@
07
0.
0&
#1703
b111 #
#1704
0B
0R
b110 U
#1705
1F
1Q
1O
#1706
0N
b100 U
#1707
1=
1M
1K
#1708
0I
b0 U
#1709
14
b1000 U
#1750
1!
#1751
0G
0>
05
0,
#1752
1@
17
1.
1&
#1753
0E
0<
03
0+
#1754
1D
1;
12
1*
#1755
0C
0:
01
0)
#1756
1(
#1800
0!
#1801
1G
1>
15
1,
#1802
0A
08
0/
0%
#1803
1B
19
10
b1111 #
#1804
0'
0S
b1000 #
#1805
b1001 U
1R
1H
1N
1T
1I
#1806
0P
0Q
0O
0M
0K
0J
0L
b1 U
#1807
1+
1O
b1111 U
1K
#1808
0+
b1001 U
#1850
1!
#1851
0G
0>
05
0,
#1852
1A
18
1/
1%
#1853
0F
#1854
1E
#1855
0D
#1856
1C
#1900
0!
#1901
1G
1>
15
1,
#1902
0@
08
0/
0%
#1903
b1001 #
#1904
0B
b1000 U
#1905
1F
1P
#1906
0O
#1907
b1010 U
#1950
1!
#1951
0G
0>
05
0,
#1952
1@
18
1/
1%
#1953
0E
0=
#1954
1D
1<
#1955
0C
0;
#1956
1:
#2000
0!
#2001
1G
1>
15
1,
#2002
0A
07
0/
0%
#2003
1B
b1011 #
#2004
09
0R
0H
b1010 #
#2005
1R
b1011 U
1Q
1O
1L
#2006
0Q
0O
0L
b1001 U
0K
#2007
1=
1K
b1111 U
#2008
0=
b1011 U
#2050
1!
#2051
0G
0>
05
0,
#2052
1A
17
1/
1%
#2053
0F
#2054
1E
#2055
0D
#2056
1C
#2100
0!
#2101
1G
1>
15
1,
#2102
0@
07
0/
0%
#2103
b1011 #
#2104
0B
0R
b1010 U
#2105
1F
1Q
1O
1L
#2106
b1000 U
0K
#2107
1=
b1100 U
#2150
1!
#2151
0G
0>
05
0,
#2152
1@
17
1/
1%
#2153
0E
0<
04
#2154
1D
1;
13
#2155
0C
0:
02
#2156
11
#2200
0!
#2201
1G
1>
15
1,
#2202
0A
08
0.
0%
#2203
1B
19
b1111 #
#2204
00
0N
0T
b1100 #
#2205
b1101 U
1R
1H
1M
1K
1J
#2206
0P
0Q
0O
b1 U
#2207
14
1+
1O
1N
b11 U
#2208
b1 U
0M
0K
0J
#2209
b1101 U
#2210
04
0+
#2250
1!
#2251
0G
0>
05
0,
#2252
1A
18
1.
1%
#2253
0F
#2254
1E
#2255
0D
#2256
1C
#2300
0!
#2301
1G
1>
15
1,
#2302
0@
08
0.
0%
#2303
b1101 #
#2304
0B
b1100 U
#2305
1F
1P
#2306
0O
#2307
b1110 U
#2350
1!
#2351
0G
0>
05
0,
#2352
1@
18
1.
1%
#2353
0E
0=
#2354
1D
1<
#2355
0C
0;
#2356
1:
#2400
0!
#2401
1G
1>
15
1,
#2402
0A
07
0.
0%
#2403
1B
b1111 #
#2404
09
0R
0H
b1110 #
#2405
1R
b1111 U
1Q
1O
#2406
0Q
0O
0N
b1101 U
#2407
1=
1N
b1111 U
1M
1K
1J
#2408
0=
0M
0K
0J
b11 U
#2409
14
1+
b1111 U
#2410
04
0+
#2450
1!
#2451
0G
0>
05
0,
#2452
1A
17
1.
1%
#2453
0F
#2454
1E
#2455
0D
#2456
1C
#2500
0!
#2501
1G
1>
15
1,
#2502
0@
07
0.
0%
#2503
b1111 #
#2504
0B
0R
b1110 U
#2505
1F
1Q
1O
#2506
0N
b1100 U
#2507
1=
1M
1K
1J
#2508
b0 U
#2509
14
1+
#2550
1!
#2551
0G
0>
05
0,
#2552
1@
17
1.
1%
#2553
0E
0<
03
0*
#2554
1D
1;
12
1)
#2555
0C
0:
01
0(
#2600
0!
#2601
1G
1>
15
1,
#2602
0A
08
0/
0&
#2603
1B
19
10
1'
#2604
b0 #
#2605
b1 U
1R
1H
1N
1T
1S
#2606
0P
0Q
0O
0M
0K
0L
0I
#2607
1O
1I
1K
b1111 U
#2608
b1 U
#2650
1!
#2651
0G
0>
05
0,
#2652
1A
18
1/
1&
#2653
0F
#2654
1E
#2655
0D
#2656
1C
#2700
0!
#2701
1G
1>
15
1,
#2702
0@
08
0/
0&
#2703
b1 #
#2704
0B
b0 U
#2705
1F
1P
#2706
0O
#2707
b10 U
#2750
1!
#2751
0G
0>
05
0,
#2752
1@
18
1/
1&
#2753
0E
0=
#2754
1D
1<
#2755
0C
0;
#2756
1:
#2800
0!
#2801
1G
1>
15
1,
#2802
0A
07
0/
0&
#2803
1B
b11 #
#2804
09
0R
0H
b10 #
#2805
1R
b11 U
1Q
1O
1L
#2806
0Q
0O
0L
b1 U
0K
#2807
1=
1K
b111 U
#2808
0=
b11 U
#2850
1!
#2851
0G
0>
05
0,
#2852
1A
17
1/
1&
#2853
0F
#2854
1E
#2855
0D
#2856
1C
#2900
0!
#2901
1G
1>
15
1,
#2902
0@
07
0/
0&
#2903
b11 #
#2904
0B
0R
b10 U
#2905
1F
1Q
1O
1L
#2906
b0 U
0K
#2907
1=
b100 U
#2950
1!
#2951
0G
0>
05
0,
#2952
1@
17
1/
1&
#2953
0E
0<
04
#2954
1D
1;
13
#2955
0C
0:
02
#2956
11
#3000
0!
#3001
1G
1>
15
1,
#3002
0A
08
0.
0&
#3003
1B
19
b111 #
#3004
00
0N
0T
b100 #
#3005
b101 U
1R
1H
1M
1K
#3006
0P
0Q
0O
0I
b1 U
#3007
14
1O
1N
b1011 U
#3008
b1001 U
0M
0K
#3009
1I
b1101 U
#3010
04
b101 U
#3050
1!
#3051
0G
0>
05
0,
#3052
1A
18
1.
1&
#3053
0F
#3054
1E
#3055
0D
#3056
1C
#3100
0!
#3101
1G
1>
15
1,
#3102
0@
08
0.
0&
#3103
b101 #
#3104
0B
b100 U
#3105
1F
1P
#3106
0O
#3107
b110 U
#3150
1!
#3151
0G
0>
05
0,
#3152
1@
18
1.
1&
#3153
0E
0=
#3154
1D
1<
#3155
0C
0;
#3156
1:
#3200
0!
#3201
1G
1>
15
1,
#3202
0A
07
0.
0&
#3203
1B
b111 #
#3204
09
0R
0H
b110 #
#3205
1R
b111 U
1Q
1O
#3206
0Q
0O
0N
b101 U
#3207
1=
1N
b111 U
1M
1K
#3208
0=
0M
0K
0I
b11 U
#3209
14
1I
b1111 U
#3210
04
b111 U
#3250
1!
#3251
0G
0>
05
0,
#3252
1A
17
1.
1&
#3253
0F
#3254
1E
#3255
0D
#3256
1C
#3300
0!
#3301
1G
1>
15
1,
#3302
0@
07
0.
0&
#3303
b111 #
#3304
0B
0R
b110 U
#3305
1F
1Q
1O
#3306
0N
b100 U
#3307
1=
1M
1K
#3308
0I
b0 U
#3309
14
b1000 U
#3350
1!
#3351
0G
0>
05
0,
#3352
1@
17
1.
1&
#3353
0E
0<
03
0+
#3354
1D
1;
12
1*
#3355
0C
0:
01
0)
#3356
1(
#3400
0!
#3401
1G
1>
15
1,
#3402
0A
08
0/
0%
#3403
1B
19
10
b1111 #
#3404
0'
0S
b1000 #
#3405
b1001 U
1R
1H
1N
1T
1I
#3406
0P
0Q
0O
0M
0K
0J
0L
b1 U
#3407
1+
1O
b1111 U
1K
#3408
0+
b1001 U
#3450
1!
#3451
0G
0>
05
0,
#3452
1A
18
1/
1%
#3453
0F
#3454
1E
#3455
0D
#3456
1C
#3500
0!
#3501
1G
1>
15
1,
#3502
0@
08
0/
0%
#3503
b1001 #
#3504
0B
b1000 U
#3505
1F
1P
#3506
0O
#3507
b1010 U
#3550
1!
#3551
0G
0>
05
0,
#3552
1@
18
1/
1%
#3553
0E
0=
#3554
1D
1<
#3555
0C
0;
#3556
1:
#3600
0!
#3601
1G
1>
15
1,
#3602
0A
07
0/
0%
#3603
1B
b1011 #
#3604
09
0R
0H
b1010 #
#3605
1R
b1011 U
1Q
1O
1L
#3606
0Q
0O
0L
b1001 U
0K
#3607
1=
1K
b1111 U
#3608
0=
b1011 U
#3650
1!
#3651
0G
0>
05
0,
#3652
1A
17
1/
1%
#3653
0F
#3654
1E
#3655
0D
#3656
1C
#3700
0!
#3701
1G
1>
15
1,
#3702
0@
07
0/
0%
#3703
b1011 #
#3704
0B
0R
b1010 U
#3705
1F
1Q
1O
1L
#3706
b1000 U
0K
#3707
1=
b1100 U
#3750
1!
#3751
0G
0>
05
0,
#3752
1@
17
1/
1%
#3753
0E
0<
04
#3754
1D
1;
13
#3755
0C
0:
02
#3756
11
#3800
0!
#3801
1G
1>
15
1,
#3802
0A
08
0.
0%
#3803
1B
19
b1111 #
#3804
00
0N
0T
b1100 #
#3805
b1101 U
1R
1H
1M
1K
1J
#3806
0P
0Q
0O
b1 U
#3807
14
1+
1O
1N
b11 U
#3808
b1 U
0M
0K
0J
#3809
b1101 U
#3810
04
0+
#3850
1!
#3851
0G
0>
05
0,
#3852
1A
18
1.
1%
#3853
0F
#3854
1E
#3855
0D
#3856
1C
#3900
0!
#3901
1G
1>
15
1,
#3902
0@
08
0.
0%
#3903
b1101 #
#3904
0B
b1100 U
#3905
1F
1P
#3906
0O
#3907
b1110 U
#3950
1!
#3951
0G
0>
05
0,
#3952
1@
18
1.
1%
#3953
0E
0=
#3954
1D
1<
#3955
0C
0;
#3956
1:
#4000
0!
#4001
1G
1>
15
1,
#4002
0A
07
0.
0%
#4003
1B
b1111 #
#4004
09
0R
0H
b1110 #
#4005
1R
b1111 U
1Q
1O
#4006
0Q
0O
0N
b1101 U
#4007
1=
1N
b1111 U
1M
1K
1J
#4008
0=
0M
0K
0J
b11 U
#4009
14
1+
b1111 U
#4010
04
0+
#4050
1!
#4051
0G
0>
05
0,
#4052
1A
17
1.
1%
#4053
0F
#4054
1E
#4055
0D
#4056
1C
#4100
0!
#4101
1G
1>
15
1,
#4102
0@
07
0.
0%
#4103
b1111 #
#4104
0B
0R
b1110 U
#4105
1F
1Q
1O
#4106
0N
b1100 U
#4107
1=
1M
1K
1J
#4108
b0 U
#4109
14
1+
#4150
1!
#4151
0G
0>
05
0,
#4152
1@
17
1.
1%
#4153
0E
0<
03
0*
#4154
1D
1;
12
1)
#4155
0C
0:
01
0(
#4200
0!
#4201
1G
1>
15
1,
#4202
0A
08
0/
0&
#4203
1B
19
10
1'
#4204
b0 #
#4205
b1 U
1R
1H
1N
1T
1S
#4206
0P
0Q
0O
0M
0K
0L
0I
#4207
1O
1I
1K
b1111 U
#4208
b1 U
#4250
1!
#4251
0G
0>
05
0,
#4252
1A
18
1/
1&
#4253
0F
#4254
1E
#4255
0D
#4256
1C
#4300
0!
#4301
1G
1>
15
1,
#4302
0@
08
0/
0&
#4303
b1 #
#4304
0B
b0 U
#4305
1F
1P
#4306
0O
#4307
b10 U
#4350
1!
#4351
0G
0>
05
0,
#4352
1@
18
1/
1&
#4353
0E
0=
#4354
1D
1<
#4355
0C
0;
#4356
1:
#4400
0!
#4401
1G
1>
15
1,
#4402
0A
07
0/
0&
#4403
1B
b11 #
#4404
09
0R
0H
b10 #
#4405
1R
b11 U
1Q
1O
1L
#4406
0Q
0O
0L
b1 U
0K
#4407
1=
1K
b111 U
#4408
0=
b11 U
#4450
1!
#4451
0G
0>
05
0,
#4452
1A
17
1/
1&
#4453
0F
