OnlyNandYosysSynth/test/NAND.v
module NAND(
    input wire A,
    input wire B,
    output wire Y
);

assign #1 Y = ~(A&B);

endmodule

OnlyNandYosysSynth/test/synth_dff.v
/* Generated by Yosys 0.9 (git sha1 1979e0b) */

(* top =  1  *)
(* src = "dff.v:1" *)
module dff(C, R, D, Q);
  (* src = "dff.v:8|all2nand.v:18" *)
  wire _00_;
  (* src = "dff.v:8|all2nand.v:17" *)
  wire _01_;
  (* src = "dff.v:8|all2nand.v:19" *)
  wire _02_;
  (* src = "dff.v:8|all2nand.v:20" *)
  wire _03_;
  (* src = "dff.v:8|all2nand.v:21" *)
  wire _04_;
  (* src = "dff.v:8|all2nand.v:24" *)
  wire _05_;
  (* src = "dff.v:8|all2nand.v:22" *)
  wire _06_;
  (* src = "dff.v:8|all2nand.v:23" *)
  wire _07_;
  (* src = "dff.v:8|all2nand.v:15" *)
  wire _08_;
  (* src = "dff.v:2" *)
  input C;
  (* src = "dff.v:4" *)
  input D;
  (* src = "dff.v:5" *)
  output Q;
  (* src = "dff.v:3" *)
  input R;
  (* module_not_derived = 32'd1 *)
  (* src = "dff.v:8|all2nand.v:26|all2nand.v:3" *)
  NAND _09_ (
    .A(R),
    .B(R),
    .Y(_08_)
  );
  (* module_not_derived = 32'd1 *)
  (* src = "dff.v:8|all2nand.v:27" *)
  NAND _10_ (
    .A(_08_),
    .B(C),
    .Y(_00_)
  );
  (* module_not_derived = 32'd1 *)
  (* src = "dff.v:8|all2nand.v:28" *)
  NAND _11_ (
    .A(D),
    .B(_06_),
    .Y(_01_)
  );
  (* module_not_derived = 32'd1 *)
  (* src = "dff.v:8|all2nand.v:29" *)
  NAND _12_ (
    .A(_01_),
    .B(_07_),
    .Y(_02_)
  );
  (* module_not_derived = 32'd1 *)
  (* src = "dff.v:8|all2nand.v:30" *)
  NAND _13_ (
    .A(_02_),
    .B(_08_),
    .Y(_03_)
  );
  (* module_not_derived = 32'd1 *)
  (* src = "dff.v:8|all2nand.v:31" *)
  NAND _14_ (
    .A(_03_),
    .B(_03_),
    .Y(_04_)
  );
  (* module_not_derived = 32'd1 *)
  (* src = "dff.v:8|all2nand.v:32" *)
  NAND _15_ (
    .A(_03_),
    .B(_00_),
    .Y(_06_)
  );
  (* module_not_derived = 32'd1 *)
  (* src = "dff.v:8|all2nand.v:33" *)
  NAND _16_ (
    .A(_04_),
    .B(_00_),
    .Y(_07_)
  );
  (* module_not_derived = 32'd1 *)
  (* src = "dff.v:8|all2nand.v:34" *)
  NAND _17_ (
    .A(_06_),
    .B(Q),
    .Y(_05_)
  );
  (* module_not_derived = 32'd1 *)
  (* src = "dff.v:8|all2nand.v:35" *)
  NAND _18_ (
    .A(_07_),
    .B(_05_),
    .Y(Q)
  );
endmodule

OnlyNandYosysSynth/test/dff_tb.v
//iverilog -o .\out\dff_tb .\dff_tb.v .\synth_dff.v. .\DFF_PP0.v .\NOT.v .\NAND.v
module dff_tb;
    reg C, R, D;
    wire Q;
    dff u1 (.C(C), .R(R), .D(D), .Q(Q));
    
    initial begin  
        C=0;
        forever #50 C=~C;
    end

    initial begin
        $dumpfile("dff_tb.vcd");
        $dumpvars(0,u1);
        $display("start");
        R = 0;
        D = 1;
        #130
        D = 0;
        #700;
        D = 1;
        #220;
        D = 1;
        #110;
        R=1;
        #235
        D = 0;
        #400;
        D = 1;
        #300;
        R=0;
        #100;
        D = 0;
        #400;
        D = 1;
        #250
        D=0;
        #50;
         D = 0;
        #420;
        D = 1;
        #210
        D=0;
        #232;
        D=0;
        #115;
        D=1;
        $display("finish");
        $finish;
    end
endmodule

OnlyNandYosysSynth/test/out/dff_tb.vcd
$date
	Fri Aug 25 11:31:35 2023
$end
$version
	Icarus Verilog
$end
$timescale
	1s
$end
$scope module dff_tb $end
$scope module u1 $end
$var wire 1 ! C $end
$var wire 1 " D $end
$var wire 1 # R $end
$var wire 1 $ _18_ $end
$var wire 1 % _17_ $end
$var wire 1 & _16_ $end
$var wire 1 ' _15_ $end
$var wire 1 ( _14_ $end
$var wire 1 ) _13_ $end
$var wire 1 * _12_ $end
$var wire 1 + _11_ $end
$var wire 1 , _10_ $end
$var wire 1 - _09_ $end
$var wire 1 . _08_ $end
$var wire 1 / _07_ $end
$var wire 1 0 _06_ $end
$var wire 1 1 _05_ $end
$var wire 1 2 _04_ $end
$var wire 1 3 _03_ $end
$var wire 1 4 _02_ $end
$var wire 1 5 _01_ $end
$var wire 1 6 _00_ $end
$var wire 1 7 Q $end
$scope module _19_ $end
$var wire 1 ' Y $end
$var wire 1 2 B $end
$var wire 1 2 A $end
$upscope $end
$scope module _20_ $end
$var wire 1 * Y $end
$var wire 1 + B $end
$var wire 1 + A $end
$upscope $end
$scope module _21_ $end
$var wire 1 * A $end
$var wire 1 * B $end
$var wire 1 ) Y $end
$upscope $end
$scope module _22_ $end
$var wire 1 ) A $end
$var wire 1 ) B $end
$var wire 1 ( Y $end
$upscope $end
$scope module _23_ $end
$var wire 1 $ Y $end
$var wire 1 % B $end
$var wire 1 % A $end
$upscope $end
$scope module _24_ $end
$var wire 1 2 Y $end
$var wire 1 5 B $end
$var wire 1 5 A $end
$upscope $end
$scope module _25_ $end
$var wire 1 ! A $end
$var wire 1 ! B $end
$var wire 1 / Y $end
$upscope $end
$scope module _26_ $end
$var wire 1 / A $end
$var wire 1 / B $end
$var wire 1 . Y $end
$upscope $end
$scope module _27_ $end
$var wire 1 . A $end
$var wire 1 . B $end
$var wire 1 - Y $end
$upscope $end
$scope module _28_ $end
$var wire 1 4 Y $end
$var wire 1 & B $end
$var wire 1 & A $end
$upscope $end
$scope module _29_ $end
$var wire 1 # A $end
$var wire 1 # B $end
$var wire 1 , Y $end
$upscope $end
$scope module _30_ $end
$var wire 1 , A $end
$var wire 1 , B $end
$var wire 1 + Y $end
$upscope $end
$scope module _31_ $end
$var wire 1 2 B $end
$var wire 1 1 Y $end
$var wire 1 3 A $end
$upscope $end
$scope module _32_ $end
$var wire 1 ' B $end
$var wire 1 0 Y $end
$var wire 1 3 A $end
$upscope $end
$scope module _33_ $end
$var wire 1 1 A $end
$var wire 1 7 Y $end
$var wire 1 6 B $end
$upscope $end
$scope module _34_ $end
$var wire 1 0 A $end
$var wire 1 7 B $end
$var wire 1 6 Y $end
$upscope $end
$scope module _35_ $end
$var wire 1 - A $end
$var wire 1 ! B $end
$var wire 1 & Y $end
$upscope $end
$scope module _36_ $end
$var wire 1 ( A $end
$var wire 1 # B $end
$var wire 1 % Y $end
$upscope $end
$scope module _37_ $end
$var wire 1 % A $end
$var wire 1 " B $end
$var wire 1 5 Y $end
$upscope $end
$scope module _38_ $end
$var wire 1 % A $end
$var wire 1 & B $end
$var wire 1 3 Y $end
$upscope $end
$upscope $end
$upscope $end
$enddefinitions $end
$comment Show the parameter values. $end
$dumpall
$end
#0
$dumpvars
x7
x6
x5
x4
x3
x2
x1
x0
x/
x.
x-
x,
x+
x*
x)
x(
x'
x&
x%
x$
0#
1"
0!
$end
#1
1%
1&
1,
1/
#2
05
0$
03
04
0+
0.
#3
12
10
11
1*
1-
#4
0'
0)
#5
1(
#50
1!
#51
0/
0&
#52
1.
13
14
#53
0-
01
#54
1&
17
#55
03
04
06
#56
11
#100
0!
#101
1/
#102
0.
#103
1-
#130
0"
#131
15
#132
02
#133
1'
#150
1!
#151
0/
0&
#152
1.
13
14
#153
0-
00
#154
1&
16
#155
03
04
07
#156
10
#200
0!
#201
1/
#202
0.
#203
1-
#250
1!
#251
0/
0&
#252
1.
13
14
#253
0-
00
#254
1&
#255
03
04
#256
10
#300
0!
#301
1/
#302
0.
#303
1-
#350
1!
#351
0/
0&
#352
1.
13
14
#353
0-
00
#354
1&
#355
03
04
#356
10
#400
0!
#401
1/
#402
0.
#403
1-
#450
1!
#451
0/
0&
#452
1.
13
14
#453
0-
00
#454
1&
#455
03
04
#456
10
#500
0!
#501
1/
#502
0.
#503
1-
#550
1!
#551
0/
0&
#552
1.
13
14
#553
0-
00
#554
1&
#555
03
04
#556
10
#600
0!
#601
1/
#602
0.
#603
1-
#650
1!
#651
0/
0&
#652
1.
13
14
#653
0-
00
#654
1&
#655
03
04
#656
10
#700
0!
#701
1/
#702
0.
#703
1-
#750
1!
#751
0/
0&
#752
1.
13
14
#753
0-
00
#754
1&
#755
03
04
#756
10
#800
0!
#801
1/
#802
0.
#803
1-
#830
1"
#831
05
#832
12
#833
0'
#850
1!
#851
0/
0&
#852
1.
13
14
#853
0-
01
#854
1&
17
#855
03
04
06
#856
11
#900
0!
#901
1/
#902
0.
#903
1-
#950
1!
#951
0/
0&
#952
1.
13
14
#953
0-
01
#954
1&
#955
03
04
#956
11
#1000
0!
#1001
1/
#1002
0.
#1003
1-
#1050
1!
#1051
0/
0&
#1052
1.
13
14
#1053
0-
01
#1054
1&
#1055
03
04
#1056
11
#1100
0!
#1101
1/
#1102
0.
#1103
1-
#1150
1!
#1151
0/
0&
#1152
1.
13
14
#1153
0-
01
#1154
1&
#1155
03
04
#1156
11
#1160
1#
#1161
0,
0%
#1162
1+
15
13
1$
#1163
0*
02
01
#1164
1)
11
1'
#1165
0(
00
#1166
1%
16
#1167
05
03
0$
07
#1168
12
10
#1169
0'
#1200
0!
#1201
1/
#1202
0.
#1203
1-
#1250
1!
#1251
0/
0&
#1252
1.
13
14
#1253
0-
01
#1254
1&
17
#1255
03
04
06
#1256
11
#1300
0!
#1301
1/
#1302
0.
#1303
1-
#1350
1!
#1351
0/
0&
#1352
1.
13
14
#1353
0-
01
#1354
1&
#1355
03
04
#1356
11
#1395
0"
#1396
15
#1397
02
#1398
1'
#1400
0!
#1401
1/
#1402
0.
#1403
1-
#1450
1!
#1451
0/
0&
#1452
1.
13
14
#1453
0-
00
#1454
1&
16
#1455
03
04
07
#1456
10
#1500
0!
#1501
1/
#1502
0.
#1503
1-
#1550
1!
#1551
0/
0&
#1552
1.
13
14
#1553
0-
00
#1554
1&
#1555
03
04
#1556
10
#1600
0!
#1601
1/
#1602
0.
#1603
1-
#1650
1!
#1651
0/
0&
#1652
1.
13
14
#1653
0-
00
#1654
1&
#1655
03
04
#1656
10
#1700
0!
#1701
1/
#1702
0.
#1703
1-
#1750
1!
#1751
0/
0&
#1752
1.
13
14
#1753
0-
00
#1754
1&
#1755
03
04
#1756
10
#1795
1"
#1796
05
#1797
12
#1798
0'
#1800
0!
#1801
1/
#1802
0.
#1803
1-
#1850
1!
#1851
0/
0&
#1852
1.
13
14
#1853
0-
01
#1854
1&
17
#1855
03
04
06
#1856
11
#1900
0!
#1901
1/
#1902
0.
#1903
1-
#1950
1!
#1951
0/
0&
#1952
1.
13
14
#1953
0-
01
#1954
1&
#1955
03
04
#1956
11
#2000
0!
#2001
1/
#2002
0.
#2003
1-
#2050
1!
#2051
0/
0&
#2052
1.
13
14
#2053
0-
01
#2054
1&
#2055
03
04
#2056
11
#2095
0#
#2096
1,
#2097
0+
#2098
1*
#2099
0)
#2100
1(
0!
#2101
1/
#2102
0.
#2103
1-
#2150
1!
#2151
0/
0&
#2152
1.
13
14
#2153
0-
01
#2154
1&
#2155
03
04
#2156
11
#2195
0"
#2196
15
#2197
02
#2198
1'
#2200
0!
#2201
1/
#2202
0.
#2203
1-
#2250
1!
#2251
0/
0&
#2252
1.
13
14
#2253
0-
00
#2254
1&
16
#2255
03
04
07
#2256
10
#2300
0!
#2301
1/
#2302
0.
#2303
1-
#2350
1!
#2351
0/
0&
#2352
1.
13
14
#2353
0-
00
#2354
1&
#2355
03
04
#2356
10
#2400
0!
#2401
1/
#2402
0.
#2403
1-
#2450
1!
#2451
0/
0&
#2452
1.
13
14
#2453
0-
00
#2454
1&
#2455
03
04
#2456
10
#2500
0!
#2501
1/
#2502
0.
#2503
1-
#2550
1!
#2551
0/
0&
#2552
1.
13
14
#2553
0-
00
#2554
1&
#2555
03
04
#2556
10
#2595
1"
#2596
05
#2597
12
#2598
0'
#2600
0!
#2601
1/
#2602
0.
#2603
1-
#2650
1!
#2651
0/
0&
#2652
1.
13
14
#2653
0-
01
#2654
1&
17
#2655
03
04
06
#2656
11
#2700
0!
#2701
1/
#2702
0.
#2703
1-
#2750
1!
#2751
0/
0&
#2752
1.
13
14
#2753
0-
01
#2754
1&
#2755
03
04
#2756
11
#2800
0!
#2801
1/
#2802
0.
#2803
1-
#2845
0"
#2846
15
#2847
02
#2848
1'
#2850
1!
#2851
0/
0&
#2852
1.
13
14
#2853
0-
00
#2854
1&
16
#2855
03
04
07
#2856
10
#2900
0!
#2901
1/
#2902
0.
#2903
1-
#2950
1!
#2951
0/
0&
#2952
1.
13
14
#2953
0-
00
#2954
1&
#2955
03
04
#2956
10
#3000
0!
#3001
1/
#3002
0.
#3003
1-
#3050
1!
#3051
0/
0&
#3052
1.
13
14
#3053
0-
00
#3054
1&
#3055
03
04
#3056
10
#3100
0!
#3101
1/
#3102
0.
#3103
1-
#3150
1!
#3151
0/
0&
#3152
1.
13
14
#3153
0-
00
#3154
1&
#3155
03
04
#3156
10
#3200
0!
#3201
1/
#3202
0.
#3203
1-
#3250
1!
#3251
0/
0&
#3252
1.
13
14
#3253
0-
00
#3254
1&
#3255
03
04
#3256
10
#3300
0!
#3301
1/
#3302
0.
#3303
1-
#3315
1"
#3316
05
#3317
12
#3318
0'
#3350
1!
#3351
0/
0&
#3352
1.
13
14
#3353
0-
01
#3354
1&
17
#3355
03
04
06
#3356
11
#3400
0!
#3401
1/
#3402
0.
#3403
1-
#3450
1!
#3451
0/
0&
#3452
1.
13
14
#3453
0-
01
#3454
1&
#3455
03
04
#3456
11
#3500
0!
#3501
1/
#3502
0.
#3503
1-
#3525
0"
#3526
15
#3527
02
#3528
1'
#3550
1!
#3551
0/
0&
#3552
1.
13
14
#3553
0-
00
#3554
1&
16
#3555
03
04
07
#3556
10
#3600
0!
#3601
1/
#3602
0.
#3603
1-
#3650
1!
#3651
0/
0&
#3652
1.
13
14
#3653
0-
00
#3654
1&
#3655
03
04
#3656
10
#3700
0!
#3701
1/
#3702
0.
#3703
1-
#3750
1!
#3751
0/
0&
#3752
1.
13
14
#3753
0-
00
#3754
1&
#3755
03
04
#3756
10
#3800
0!
#3801
1/
#3802
0.
#3803
1-
#3850
1!
#3851
0/
0&
#3852
1.
13
14
#3853
0-
00
#3854
1&
#3855
03
04
#3856
10
#3872
1"
