OnlyNandYosysSynth/test/NAND.v
module NAND(
    input wire A,
    input wire B,
    output wire Y
);

assign #1 Y = ~(A&B);

endmodule

OnlyNandYosysSynth/test/NOT.v
module NOT (input A, output Y);
	NAND u1 (.A(A), .B(A), .Y(Y));
endmodule

OnlyNandYosysSynth/test/DFF_PP0.v
/*DFF WITH ASYNC RESET with the following behaviour
module \$_DFF_PP0_ (D, C, R, Q);
input D, C, R;
output reg Q;
always @(posedge c) begin
	if (R == 1)
		Q <= 0;
end
always begin
	if (R == 1)
		Q <= 0;
end
endmodule
*/
module DFF_PP0(input C, input D, input R, output Q);
    wire not_R;
    wire C_nand_R;
    wire D_nand_Feedback;
    wire C_nand_not_R;
    wire nand_1;
    wire nand_2;
    wire nand_3;
    wire nand_dff_1;
    wire nand_dff_2;
    wire nand_QBAR;

    NOT u0 (.A(R), .Y(not_R));
    NAND u1 (.A(not_R), .B(C), .Y(C_nand_not_R));
    NAND u2 (.A(D), .B(nand_dff_1), .Y(D_nand_Feedback));
    NAND u3 (.A(D_nand_Feedback), .B(nand_dff_2), .Y(nand_1));
    NAND u4 (.A(nand_1), .B(not_R), .Y(nand_2));
    NAND u5 (.A(nand_2), .B(nand_2), .Y(nand_3));
    NAND u6 (.A(nand_2), .B(C_nand_not_R), .Y(nand_dff_1));
    NAND u7 (.A(nand_3), .B(C_nand_not_R), .Y(nand_dff_2));
    NAND u8 (.A(nand_dff_1), .B(Q), .Y(nand_QBAR));
    NAND u9 (.A(nand_dff_2), .B(nand_QBAR), .Y(Q));
endmodule


/* not optimized at all async reset dff rising edges
module DFF_PP0(input C, input D, input R, output Q);
    wire nand1_out; // output from nand1
    wire nand2_out; // output from nand2
    wire not_D;
    wire QBAR;

    wire not_R;
    wire and_R;
    wire in;

    wire clock_edge, not_clock_edge, clock_edge_or_reset;
    wire reset_edge, not_reset_edge;
    wire not_1, not_2, not_3, not_4;
    wire not_5, not_6, not_7, not_8;
    
    // clock edge detection
    NOT n3 (.A(C), .Y(not_1));
    NOT n4 (.A(not_1), .Y(not_2));
    NOT n5 (.A(not_2), .Y(not_3));
    NAND u5 (.A(not_3), .B(C), .Y(not_clock_edge));
    NOT n7 (.A(not_clock_edge), .Y(clock_edge));

    // reset edge detection
    NOT n8 (.A(R), .Y(not_4));
    NOT n9 (.A(not_4), .Y(not_5));
    NOT n10 (.A(not_5), .Y(not_6));
    NOT n11 (.A(not_6), .Y(not_7));
    NOT n12 (.A(not_7), .Y(not_8));
    NAND u6 (.A(not_8), .B(R), .Y(not_reset_edge));
    NOT n13 (.A(not_reset_edge), .Y(reset_edge));

    // reset implementation in = D&~R;
    NAND u7 (.A(not_reset_edge), .B(D), .Y(and_R));
    NOT n14 (.A(and_R), .Y(in));

    // also edge detected will be 1 if reset is pressed c= c | R
    NAND u8 (.A(not_reset_edge), .B(not_clock_edge), .Y(clock_edge_or_reset));

    // dff
    NOT n1 (.A(in), .Y(not_D));
    NAND u1 (.A(clock_edge_or_reset), .B(in), .Y(nand1_out));
    NAND u2 (.A(clock_edge_or_reset), .B(not_D), .Y(nand2_out));
    NAND u3 (.A(nand1_out), .B(QBAR), .Y(Q));
    NAND u4 (.A(nand2_out), .B(Q), .Y(QBAR));

endmodule
*/

/*dff latch without reset tested
module DFF_PP0(input C, input D, input R, output Q);
    wire nand1_out; // output from nand1
    wire nand2_out; // output from nand2
    wire not_D;
    wire QBAR;

    NOT n1 (.A(D), .Y(not_D));
    NAND u1 (.A(C), .B(D), .Y(nand1_out));
    NAND u2 (.A(C), .B(not_D), .Y(nand2_out));
    NAND u3 (.A(nand1_out), .B(QBAR), .Y(Q));
    NAND u4 (.A(nand2_out), .B(Q), .Y(QBAR));
endmodule
*/

/*dff without reset, but with edge detection. It's signal doesnt last enough time (1u)
when atlest 3 u is needed for DFF. Must find a way to implement signal extension using logic gates.
module DFF_PP0(input C, input D, input R, output Q);
    wire nand1_out; // output from nand1
    wire nand2_out; // output from nand2
    wire not_D;
    wire QBAR;

    wire edge_detected, not_edgedetected;
    wire not_1, not_2, not_3, not_4;
    //edge detection
    NOT n3 (.A(C), .Y(not_1));
    NOT n4 (.A(not_1), .Y(not_2));
    NOT n5 (.A(not_2), .Y(not_3));
    NAND u5 (.A(not_3), .B(C), .Y(not_edgedetected));
    NOT n7 (.A(not_edgedetected), .Y(edge_detected));

    NOT n1 (.A(D), .Y(not_D));
    NAND u1 (.A(edge_detected), .B(D), .Y(nand1_out));
    NAND u2 (.A(edge_detected), .B(not_D), .Y(nand2_out));
    NAND u3 (.A(nand1_out), .B(QBAR), .Y(Q));
    NAND u4 (.A(nand2_out), .B(Q), .Y(QBAR));
endmodule
*/

/*SYNCRONOUS RESET IF R=1
module DFF_PP0(input C, input D, input R, output Q);
    wire nand1_out; // output from nand1
    wire nand2_out; // output from nand2
    wire not_D;
    wire QBAR;

    wire not_R;
    wire and_R;
    wire in;

    wire edge_detected, not_edgedetected;
    wire not_1, not_2, not_3, not_4;
    
    //edge detection
    NOT n3 (.A(C), .Y(not_1));
    NOT n4 (.A(not_1), .Y(not_2));
    NOT n5 (.A(not_2), .Y(not_3));
    NAND u5 (.A(not_3), .B(C), .Y(not_edgedetected));
    NOT n7 (.A(not_edgedetected), .Y(edge_detected));

    //reset implementation in = D&~R
    NOT n8 (.A(R), .Y(not_R));
    NAND u6 (.A(not_R), .B(D), .Y(and_R));
    NOT n9 (.A(and_R), .Y(in));

    //dff
    NOT n1 (.A(in), .Y(not_D));
    NAND u1 (.A(edge_detected), .B(in), .Y(nand1_out));
    NAND u2 (.A(edge_detected), .B(not_D), .Y(nand2_out));
    NAND u3 (.A(nand1_out), .B(QBAR), .Y(Q));
    NAND u4 (.A(nand2_out), .B(Q), .Y(QBAR));
endmodule
*/

/* async reset when R = 1 still left to add posedge
module DFF_PP0(input C, input D, input R, output Q);
    wire nand1_out; // output from nand1
    wire nand2_out; // output from nand2
    wire not_D;
    wire QBAR;

    wire not_R;
    wire and_R;
    wire in;

    wire clock_edge, not_clock_edge, clock_edge_or_reset;
    wire not_1, not_2, not_3, not_4;
    
    //clock edge detection
    NOT n3 (.A(C), .Y(not_1));
    NOT n4 (.A(not_1), .Y(not_2));
    NOT n5 (.A(not_2), .Y(not_3));
    NAND u5 (.A(not_3), .B(C), .Y(not_clock_edge));
    NOT n7 (.A(not_clock_edge), .Y(clock_edge));

    //reset implementation in = D&~R;
    NOT n8 (.A(R), .Y(not_R));
    NAND u6 (.A(not_R), .B(D), .Y(and_R));
    NOT n9 (.A(and_R), .Y(in));

    //also edge detected will be 1 if reset is pressed c= c | R
    NAND n10 (.A(not_R), .B(not_clock_edge), .Y(clock_edge_or_reset));

    //dff
    NOT n1 (.A(in), .Y(not_D));
    NAND u1 (.A(clock_edge_or_reset), .B(in), .Y(nand1_out));
    NAND u2 (.A(clock_edge_or_reset), .B(not_D), .Y(nand2_out));
    NAND u3 (.A(nand1_out), .B(QBAR), .Y(Q));
    NAND u4 (.A(nand2_out), .B(Q), .Y(QBAR));
endmodule
*/

OnlyNandYosysSynth/test/DFF_PP0_tb.v
//iverilog -o .\out\DFF_PP0_tb .\DFF_PP0_tb.v .\DFF_PP0.v .\NOT.v .\NAND.v
module DFF_PP0_tb;
    reg D, C, R;
    wire Q;
    DFF_PP0 u1(.C(C), .D(D), .R(R), .Q(Q));
    
    initial begin  
        C=0;
        forever #50 C=~C;
    end

    initial begin
        $dumpfile("DFF_PP0_tb.vcd");
        $dumpvars(3,C,D,R,Q,u1);
        $display("start");
        R = 0;
        D = 1;
        #130
        D = 0;
        #700;
        D = 1;
        #220;
        D = 1;
        #110;
        R=1;
        #235
        D = 0;
        #400;
        D = 1;
        #300;
        R=0;
        #100;
        D = 0;
        #400;
        D = 1;
        #250
        D=0;
        #50;
         D = 0;
        #420;
        D = 1;
        #210
        D=0;
        #232;
        D=0;
        #115;
        D=1;
        $display("finish");
        $finish;
    end
endmodule

OnlyNandYosysSynth/test/out/DFF_PP0_tb.vcd
$date
	Tue Aug 29 16:03:16 2023
$end
$version
	Icarus Verilog
$end
$timescale
	1s
$end
$scope module DFF_PP0_tb $end
$var reg 1 ! C $end
$upscope $end
$scope module DFF_PP0_tb $end
$var reg 1 " D $end
$upscope $end
$scope module DFF_PP0_tb $end
$var reg 1 # R $end
$upscope $end
$scope module DFF_PP0_tb $end
$var wire 1 $ Q $end
$upscope $end
$scope module DFF_PP0_tb $end
$scope module u1 $end
$var wire 1 ! C $end
$var wire 1 " D $end
$var wire 1 # R $end
$var wire 1 % not_R $end
$var wire 1 & nand_dff_2 $end
$var wire 1 ' nand_dff_1 $end
$var wire 1 ( nand_QBAR $end
$var wire 1 ) nand_3 $end
$var wire 1 * nand_2 $end
$var wire 1 + nand_1 $end
$var wire 1 $ Q $end
$var wire 1 , D_nand_Feedback $end
$var wire 1 - C_nand_not_R $end
$scope module u0 $end
$var wire 1 # A $end
$var wire 1 % Y $end
$scope module u1 $end
$var wire 1 # A $end
$var wire 1 # B $end
$var wire 1 % Y $end
$upscope $end
$upscope $end
$scope module u1 $end
$var wire 1 % A $end
$var wire 1 ! B $end
$var wire 1 - Y $end
$upscope $end
$scope module u2 $end
$var wire 1 " A $end
$var wire 1 , Y $end
$var wire 1 ' B $end
$upscope $end
$scope module u3 $end
$var wire 1 , A $end
$var wire 1 + Y $end
$var wire 1 & B $end
$upscope $end
$scope module u4 $end
$var wire 1 + A $end
$var wire 1 % B $end
$var wire 1 * Y $end
$upscope $end
$scope module u5 $end
$var wire 1 * A $end
$var wire 1 * B $end
$var wire 1 ) Y $end
$upscope $end
$scope module u6 $end
$var wire 1 * A $end
$var wire 1 - B $end
$var wire 1 ' Y $end
$upscope $end
$scope module u7 $end
$var wire 1 ) A $end
$var wire 1 - B $end
$var wire 1 & Y $end
$upscope $end
$scope module u8 $end
$var wire 1 ' A $end
$var wire 1 ( Y $end
$var wire 1 $ B $end
$upscope $end
$scope module u9 $end
$var wire 1 & A $end
$var wire 1 ( B $end
$var wire 1 $ Y $end
$upscope $end
$upscope $end
$upscope $end
$enddefinitions $end
$comment Show the parameter values. $end
$dumpall
$end
#0
$dumpvars
x-
x,
x+
x*
x)
x(
x'
x&
x%
x$
0#
1"
0!
$end
#1
1-
1%
#50
1!
#51
0-
#52
1'
1&
#53
0,
#54
1+
#55
0*
#56
1)
#100
0!
#101
1-
#102
0&
#103
1$
#104
0(
#130
0"
#131
1,
#150
1!
#151
0-
#152
1&
#153
0+
#154
1*
#155
0)
#200
0!
#201
1-
#202
0'
#203
1(
#204
0$
#250
1!
#251
0-
#252
1'
#300
0!
#301
1-
#302
0'
#350
1!
#351
0-
#352
1'
#400
0!
#401
1-
#402
0'
#450
1!
#451
0-
#452
1'
#500
0!
#501
1-
#502
0'
#550
1!
#551
0-
#552
1'
#600
0!
#601
1-
#602
0'
#650
1!
#651
0-
#652
1'
#700
0!
#701
1-
#702
0'
#750
1!
#751
0-
#752
1'
#800
0!
#801
1-
#802
0'
#830
1"
#850
1!
#851
0-
#852
1'
#853
0,
#854
1+
#855
0*
#856
1)
#900
0!
#901
1-
#902
0&
#903
1$
#904
0(
#950
1!
#951
0-
#952
1&
#1000
0!
#1001
1-
#1002
0&
#1050
1!
#1051
0-
#1052
1&
#1100
0!
#1101
1-
#1102
0&
#1150
1!
#1151
0-
#1152
1&
#1160
1#
#1161
0%
#1162
1-
1*
#1163
0&
0)
0'
#1164
1&
1(
1,
#1165
0$
0+
#1200
0!
#1250
1!
#1300
0!
#1350
1!
#1395
0"
#1400
0!
#1450
1!
#1500
0!
#1550
1!
#1600
0!
#1650
1!
#1700
0!
#1750
1!
#1795
1"
#1800
0!
#1850
1!
#1900
0!
#1950
1!
#2000
0!
#2050
1!
#2095
0#
#2096
1%
#2097
0-
#2098
1'
#2099
0,
#2100
1+
0!
#2101
0*
1-
#2102
1)
#2103
0&
#2104
1$
#2105
0(
#2150
1!
#2151
0-
#2152
1&
#2195
0"
#2196
1,
#2197
0+
#2198
1*
#2199
0)
#2200
0!
#2201
1-
#2202
0'
#2203
1(
#2204
0$
#2250
1!
#2251
0-
#2252
1'
#2300
0!
#2301
1-
#2302
0'
#2350
1!
#2351
0-
#2352
1'
#2400
0!
#2401
1-
#2402
0'
#2450
1!
#2451
0-
#2452
1'
#2500
0!
#2501
1-
#2502
0'
#2550
1!
#2551
0-
#2552
1'
#2595
1"
#2596
0,
#2597
1+
#2598
0*
#2599
1)
#2600
0!
#2601
1-
#2602
0&
#2603
1$
#2604
0(
#2650
1!
#2651
0-
#2652
1&
#2700
0!
#2701
1-
#2702
0&
#2750
1!
#2751
0-
#2752
1&
#2800
0!
#2801
1-
#2802
0&
#2845
0"
#2846
1,
#2850
1!
#2851
0-
#2852
1&
#2853
0+
#2854
1*
#2855
0)
#2900
0!
#2901
1-
#2902
0'
#2903
1(
#2904
0$
#2950
1!
#2951
0-
#2952
1'
#3000
0!
#3001
1-
#3002
0'
#3050
1!
#3051
0-
#3052
1'
#3100
0!
#3101
1-
#3102
0'
#3150
1!
#3151
0-
#3152
1'
#3200
0!
#3201
1-
#3202
0'
#3250
1!
#3251
0-
#3252
1'
#3300
0!
#3301
1-
#3302
0'
#3315
1"
#3350
1!
#3351
0-
#3352
1'
#3353
0,
#3354
1+
#3355
0*
#3356
1)
#3400
0!
#3401
1-
#3402
0&
#3403
1$
#3404
0(
#3450
1!
#3451
0-
#3452
1&
#3500
0!
#3501
1-
#3502
0&
#3525
0"
#3526
1,
#3550
1!
#3551
0-
#3552
1&
#3553
0+
#3554
1*
#3555
0)
#3600
0!
#3601
1-
#3602
0'
#3603
1(
#3604
0$
#3650
1!
#3651
0-
#3652
1'
#3700
0!
#3701
1-
#3702
0'
#3750
1!
#3751
0-
#3752
1'
#3800
0!
#3801
1-
#3802
0'
#3850
1!
#3851
0-
#3852
1'
#3872
1"
