OnlyNandYosysSynth/test/NAND.v
module NAND(
    input wire A,
    input wire B,
    output wire Y
);

assign #1 Y = ~(A&B);

endmodule

OnlyNandYosysSynth/test/NOT.v
module NOT (input A, output Y);
	NAND u1 (.A(A), .B(A), .Y(Y));
endmodule

OnlyNandYosysSynth/test/DFF_PP0.v
/*DFF WITH ASYNC RESET with the following behaviour
module \$_DFF_PP0_ (D, C, R, Q);
input D, C, R;
output reg Q;
always @(posedge C or posedge R) begin
	if (R == 1)
		Q <= 0;
	else
		Q <= D;
end
endmodule
*/
module DFF_PP0(input C, input D, input R, output Q);
    wire nand1_out; // output from nand1
    wire nand2_out; // output from nand2
    wire not_D;
    wire QBAR;

    wire not_R;
    wire and_R;
    wire in;

    wire clock_edge, not_clock_edge, clock_edge_or_reset;
    wire reset_edge, not_reset_edge;
    wire not_1, not_2, not_3, not_4;
    wire not_5, not_6, not_7, not_8;
    
    // clock edge detection
    NOT n3 (.A(C), .Y(not_1));
    NOT n4 (.A(not_1), .Y(not_2));
    NOT n5 (.A(not_2), .Y(not_3));
    NAND u5 (.A(not_3), .B(C), .Y(not_clock_edge));
    NOT n7 (.A(not_clock_edge), .Y(clock_edge));

    // reset edge detection
    NOT n8 (.A(R), .Y(not_4));
    NOT n9 (.A(not_4), .Y(not_5));
    NOT n10 (.A(not_5), .Y(not_6));
    NOT n11 (.A(not_6), .Y(not_7));
    NOT n12 (.A(not_7), .Y(not_8));
    NAND u6 (.A(not_8), .B(R), .Y(not_reset_edge));
    NOT n13 (.A(not_reset_edge), .Y(reset_edge));

    // reset implementation in = D&~R;
    NAND u7 (.A(not_reset_edge), .B(D), .Y(and_R));
    NOT n14 (.A(and_R), .Y(in));

    // also edge detected will be 1 if reset is pressed c= c | R
    NAND u8 (.A(not_reset_edge), .B(not_clock_edge), .Y(clock_edge_or_reset));

    // dff
    NOT n1 (.A(in), .Y(not_D));
    NAND u1 (.A(clock_edge_or_reset), .B(in), .Y(nand1_out));
    NAND u2 (.A(clock_edge_or_reset), .B(not_D), .Y(nand2_out));
    NAND u3 (.A(nand1_out), .B(QBAR), .Y(Q));
    NAND u4 (.A(nand2_out), .B(Q), .Y(QBAR));

endmodule

/*dff latch without reset tested
module DFF_PP0(input C, input D, input R, output Q);
    wire nand1_out; // output from nand1
    wire nand2_out; // output from nand2
    wire not_D;
    wire QBAR;

    NOT n1 (.A(D), .Y(not_D));
    NAND u1 (.A(C), .B(D), .Y(nand1_out));
    NAND u2 (.A(C), .B(not_D), .Y(nand2_out));
    NAND u3 (.A(nand1_out), .B(QBAR), .Y(Q));
    NAND u4 (.A(nand2_out), .B(Q), .Y(QBAR));
endmodule
*/

/*dff without reset, but with edge detection. It's signal doesnt last enough time (1u)
when atlest 3 u is needed for DFF. Must find a way to implement signal extension using logic gates.
module DFF_PP0(input C, input D, input R, output Q);
    wire nand1_out; // output from nand1
    wire nand2_out; // output from nand2
    wire not_D;
    wire QBAR;

    wire edge_detected, not_edgedetected;
    wire not_1, not_2, not_3, not_4;
    //edge detection
    NOT n3 (.A(C), .Y(not_1));
    NOT n4 (.A(not_1), .Y(not_2));
    NOT n5 (.A(not_2), .Y(not_3));
    NAND u5 (.A(not_3), .B(C), .Y(not_edgedetected));
    NOT n7 (.A(not_edgedetected), .Y(edge_detected));

    NOT n1 (.A(D), .Y(not_D));
    NAND u1 (.A(edge_detected), .B(D), .Y(nand1_out));
    NAND u2 (.A(edge_detected), .B(not_D), .Y(nand2_out));
    NAND u3 (.A(nand1_out), .B(QBAR), .Y(Q));
    NAND u4 (.A(nand2_out), .B(Q), .Y(QBAR));
endmodule
*/

/*SYNCRONOUS RESET IF R=1
module DFF_PP0(input C, input D, input R, output Q);
    wire nand1_out; // output from nand1
    wire nand2_out; // output from nand2
    wire not_D;
    wire QBAR;

    wire not_R;
    wire and_R;
    wire in;

    wire edge_detected, not_edgedetected;
    wire not_1, not_2, not_3, not_4;
    
    //edge detection
    NOT n3 (.A(C), .Y(not_1));
    NOT n4 (.A(not_1), .Y(not_2));
    NOT n5 (.A(not_2), .Y(not_3));
    NAND u5 (.A(not_3), .B(C), .Y(not_edgedetected));
    NOT n7 (.A(not_edgedetected), .Y(edge_detected));

    //reset implementation in = D&~R
    NOT n8 (.A(R), .Y(not_R));
    NAND u6 (.A(not_R), .B(D), .Y(and_R));
    NOT n9 (.A(and_R), .Y(in));

    //dff
    NOT n1 (.A(in), .Y(not_D));
    NAND u1 (.A(edge_detected), .B(in), .Y(nand1_out));
    NAND u2 (.A(edge_detected), .B(not_D), .Y(nand2_out));
    NAND u3 (.A(nand1_out), .B(QBAR), .Y(Q));
    NAND u4 (.A(nand2_out), .B(Q), .Y(QBAR));
endmodule
*/

/* async reset when R = 1 still left to add posedge
module DFF_PP0(input C, input D, input R, output Q);
    wire nand1_out; // output from nand1
    wire nand2_out; // output from nand2
    wire not_D;
    wire QBAR;

    wire not_R;
    wire and_R;
    wire in;

    wire clock_edge, not_clock_edge, clock_edge_or_reset;
    wire not_1, not_2, not_3, not_4;
    
    //clock edge detection
    NOT n3 (.A(C), .Y(not_1));
    NOT n4 (.A(not_1), .Y(not_2));
    NOT n5 (.A(not_2), .Y(not_3));
    NAND u5 (.A(not_3), .B(C), .Y(not_clock_edge));
    NOT n7 (.A(not_clock_edge), .Y(clock_edge));

    //reset implementation in = D&~R;
    NOT n8 (.A(R), .Y(not_R));
    NAND u6 (.A(not_R), .B(D), .Y(and_R));
    NOT n9 (.A(and_R), .Y(in));

    //also edge detected will be 1 if reset is pressed c= c | R
    NAND n10 (.A(not_R), .B(not_clock_edge), .Y(clock_edge_or_reset));

    //dff
    NOT n1 (.A(in), .Y(not_D));
    NAND u1 (.A(clock_edge_or_reset), .B(in), .Y(nand1_out));
    NAND u2 (.A(clock_edge_or_reset), .B(not_D), .Y(nand2_out));
    NAND u3 (.A(nand1_out), .B(QBAR), .Y(Q));
    NAND u4 (.A(nand2_out), .B(Q), .Y(QBAR));
endmodule
*/

OnlyNandYosysSynth/test/DFF_PP0_tb.v
//iverilog -o .\out\DFF_PP0_tb .\DFF_PP0_tb.v .\DFF_PP0.v .\NOT.v .\NAND.v
module DFF_PP0_tb;
    reg D, C, R;
    wire Q;
    DFF_PP0 u1(.C(C), .D(D), .R(R), .Q(Q));
    
    initial begin  
        C=0;
        forever #50 C=~C;
    end

    initial begin
        $dumpfile("DFF_PP0_tb.vcd");
        $dumpvars(3,C,D,R,Q,u1);
        $display("start");
        R = 0;
        D = 1;
        #130
        D = 0;
        #700;
        D = 1;
        #220;
        D = 1;
        #110;
        R=1;
        #235
        D = 0;
        #400;
        D = 1;
        #300;
        R=0;
        #100;
        D = 0;
        #400;
        D = 1;
        #250
        D=0;
        #50;
         D = 0;
        #420;
        D = 1;
        #210
        D=0;
        #232;
        D=0;
        #115;
        D=1;
        $display("finish");
        $finish;
    end
endmodule

OnlyNandYosysSynth/test/out/DFF_PP0_tb.vcd
$date
	Fri Aug 25 11:59:18 2023
$end
$version
	Icarus Verilog
$end
$timescale
	1s
$end
$scope module DFF_PP0_tb $end
$var reg 1 ! C $end
$upscope $end
$scope module DFF_PP0_tb $end
$var reg 1 " D $end
$upscope $end
$scope module DFF_PP0_tb $end
$var reg 1 # R $end
$upscope $end
$scope module DFF_PP0_tb $end
$var wire 1 $ Q $end
$upscope $end
$scope module DFF_PP0_tb $end
$scope module u1 $end
$var wire 1 ! C $end
$var wire 1 " D $end
$var wire 1 # R $end
$var wire 1 % reset_edge $end
$var wire 1 & not_reset_edge $end
$var wire 1 ' not_clock_edge $end
$var wire 1 ( not_D $end
$var wire 1 ) not_8 $end
$var wire 1 * not_7 $end
$var wire 1 + not_6 $end
$var wire 1 , not_5 $end
$var wire 1 - not_4 $end
$var wire 1 . not_3 $end
$var wire 1 / not_2 $end
$var wire 1 0 not_1 $end
$var wire 1 1 nand2_out $end
$var wire 1 2 nand1_out $end
$var wire 1 3 in $end
$var wire 1 4 clock_edge_or_reset $end
$var wire 1 5 clock_edge $end
$var wire 1 6 and_R $end
$var wire 1 7 QBAR $end
$var wire 1 $ Q $end
$scope module n1 $end
$var wire 1 ( Y $end
$var wire 1 3 A $end
$scope module u1 $end
$var wire 1 ( Y $end
$var wire 1 3 B $end
$var wire 1 3 A $end
$upscope $end
$upscope $end
$scope module n10 $end
$var wire 1 + Y $end
$var wire 1 , A $end
$scope module u1 $end
$var wire 1 + Y $end
$var wire 1 , B $end
$var wire 1 , A $end
$upscope $end
$upscope $end
$scope module n11 $end
$var wire 1 + A $end
$var wire 1 * Y $end
$scope module u1 $end
$var wire 1 + A $end
$var wire 1 + B $end
$var wire 1 * Y $end
$upscope $end
$upscope $end
$scope module n12 $end
$var wire 1 * A $end
$var wire 1 ) Y $end
$scope module u1 $end
$var wire 1 * A $end
$var wire 1 * B $end
$var wire 1 ) Y $end
$upscope $end
$upscope $end
$scope module n13 $end
$var wire 1 % Y $end
$var wire 1 & A $end
$scope module u1 $end
$var wire 1 % Y $end
$var wire 1 & B $end
$var wire 1 & A $end
$upscope $end
$upscope $end
$scope module n14 $end
$var wire 1 3 Y $end
$var wire 1 6 A $end
$scope module u1 $end
$var wire 1 3 Y $end
$var wire 1 6 B $end
$var wire 1 6 A $end
$upscope $end
$upscope $end
$scope module n3 $end
$var wire 1 ! A $end
$var wire 1 0 Y $end
$scope module u1 $end
$var wire 1 ! A $end
$var wire 1 ! B $end
$var wire 1 0 Y $end
$upscope $end
$upscope $end
$scope module n4 $end
$var wire 1 0 A $end
$var wire 1 / Y $end
$scope module u1 $end
$var wire 1 0 A $end
$var wire 1 0 B $end
$var wire 1 / Y $end
$upscope $end
$upscope $end
$scope module n5 $end
$var wire 1 / A $end
$var wire 1 . Y $end
$scope module u1 $end
$var wire 1 / A $end
$var wire 1 / B $end
$var wire 1 . Y $end
$upscope $end
$upscope $end
$scope module n7 $end
$var wire 1 5 Y $end
$var wire 1 ' A $end
$scope module u1 $end
$var wire 1 5 Y $end
$var wire 1 ' B $end
$var wire 1 ' A $end
$upscope $end
$upscope $end
$scope module n8 $end
$var wire 1 # A $end
$var wire 1 - Y $end
$scope module u1 $end
$var wire 1 # A $end
$var wire 1 # B $end
$var wire 1 - Y $end
$upscope $end
$upscope $end
$scope module n9 $end
$var wire 1 - A $end
$var wire 1 , Y $end
$scope module u1 $end
$var wire 1 - A $end
$var wire 1 - B $end
$var wire 1 , Y $end
$upscope $end
$upscope $end
$scope module u1 $end
$var wire 1 3 B $end
$var wire 1 2 Y $end
$var wire 1 4 A $end
$upscope $end
$scope module u2 $end
$var wire 1 ( B $end
$var wire 1 1 Y $end
$var wire 1 4 A $end
$upscope $end
$scope module u3 $end
$var wire 1 2 A $end
$var wire 1 $ Y $end
$var wire 1 7 B $end
$upscope $end
$scope module u4 $end
$var wire 1 1 A $end
$var wire 1 $ B $end
$var wire 1 7 Y $end
$upscope $end
$scope module u5 $end
$var wire 1 . A $end
$var wire 1 ! B $end
$var wire 1 ' Y $end
$upscope $end
$scope module u6 $end
$var wire 1 ) A $end
$var wire 1 # B $end
$var wire 1 & Y $end
$upscope $end
$scope module u7 $end
$var wire 1 & A $end
$var wire 1 " B $end
$var wire 1 6 Y $end
$upscope $end
$scope module u8 $end
$var wire 1 & A $end
$var wire 1 ' B $end
$var wire 1 4 Y $end
$upscope $end
$upscope $end
$upscope $end
$enddefinitions $end
$comment Show the parameter values. $end
$dumpall
$end
#0
$dumpvars
x7
x6
x5
x4
x3
x2
x1
x0
x/
x.
x-
x,
x+
x*
x)
x(
x'
x&
x%
x$
0#
1"
0!
$end
#1
1&
1'
1-
10
#2
06
0%
04
05
0,
0/
#3
13
11
12
1+
1.
#4
0(
0*
#5
1)
#50
1!
#51
00
0'
#52
1/
14
15
#53
0.
02
#54
1'
1$
#55
04
05
07
#56
12
#100
0!
#101
10
#102
0/
#103
1.
#130
0"
#131
16
#132
03
#133
1(
#150
1!
#151
00
0'
#152
1/
14
15
#153
0.
01
#154
1'
17
#155
04
05
0$
#156
11
#200
0!
#201
10
#202
0/
#203
1.
#250
1!
#251
00
0'
#252
1/
14
15
#253
0.
01
#254
1'
#255
04
05
#256
11
#300
0!
#301
10
#302
0/
#303
1.
#350
1!
#351
00
0'
#352
1/
14
15
#353
0.
01
#354
1'
#355
04
05
#356
11
#400
0!
#401
10
#402
0/
#403
1.
#450
1!
#451
00
0'
#452
1/
14
15
#453
0.
01
#454
1'
#455
04
05
#456
11
#500
0!
#501
10
#502
0/
#503
1.
#550
1!
#551
00
0'
#552
1/
14
15
#553
0.
01
#554
1'
#555
04
05
#556
11
#600
0!
#601
10
#602
0/
#603
1.
#650
1!
#651
00
0'
#652
1/
14
15
#653
0.
01
#654
1'
#655
04
05
#656
11
#700
0!
#701
10
#702
0/
#703
1.
#750
1!
#751
00
0'
#752
1/
14
15
#753
0.
01
#754
1'
#755
04
05
#756
11
#800
0!
#801
10
#802
0/
#803
1.
#830
1"
#831
06
#832
13
#833
0(
#850
1!
#851
00
0'
#852
1/
14
15
#853
0.
02
#854
1'
1$
#855
04
05
07
#856
12
#900
0!
#901
10
#902
0/
#903
1.
#950
1!
#951
00
0'
#952
1/
14
15
#953
0.
02
#954
1'
#955
04
05
#956
12
#1000
0!
#1001
10
#1002
0/
#1003
1.
#1050
1!
#1051
00
0'
#1052
1/
14
15
#1053
0.
02
#1054
1'
#1055
04
05
#1056
12
#1100
0!
#1101
10
#1102
0/
#1103
1.
#1150
1!
#1151
00
0'
#1152
1/
14
15
#1153
0.
02
#1154
1'
#1155
04
05
#1156
12
#1160
1#
#1161
0-
0&
#1162
1,
16
14
1%
#1163
0+
03
02
#1164
1*
12
1(
#1165
0)
01
#1166
1&
17
#1167
06
04
0%
0$
#1168
13
11
#1169
0(
#1200
0!
#1201
10
#1202
0/
#1203
1.
#1250
1!
#1251
00
0'
#1252
1/
14
15
#1253
0.
02
#1254
1'
1$
#1255
04
05
07
#1256
12
#1300
0!
#1301
10
#1302
0/
#1303
1.
#1350
1!
#1351
00
0'
#1352
1/
14
15
#1353
0.
02
#1354
1'
#1355
04
05
#1356
12
#1395
0"
#1396
16
#1397
03
#1398
1(
#1400
0!
#1401
10
#1402
0/
#1403
1.
#1450
1!
#1451
00
0'
#1452
1/
14
15
#1453
0.
01
#1454
1'
17
#1455
04
05
0$
#1456
11
#1500
0!
#1501
10
#1502
0/
#1503
1.
#1550
1!
#1551
00
0'
#1552
1/
14
15
#1553
0.
01
#1554
1'
#1555
04
05
#1556
11
#1600
0!
#1601
10
#1602
0/
#1603
1.
#1650
1!
#1651
00
0'
#1652
1/
14
15
#1653
0.
01
#1654
1'
#1655
04
05
#1656
11
#1700
0!
#1701
10
#1702
0/
#1703
1.
#1750
1!
#1751
00
0'
#1752
1/
14
15
#1753
0.
01
#1754
1'
#1755
04
05
#1756
11
#1795
1"
#1796
06
#1797
13
#1798
0(
#1800
0!
#1801
10
#1802
0/
#1803
1.
#1850
1!
#1851
00
0'
#1852
1/
14
15
#1853
0.
02
#1854
1'
1$
#1855
04
05
07
#1856
12
#1900
0!
#1901
10
#1902
0/
#1903
1.
#1950
1!
#1951
00
0'
#1952
1/
14
15
#1953
0.
02
#1954
1'
#1955
04
05
#1956
12
#2000
0!
#2001
10
#2002
0/
#2003
1.
#2050
1!
#2051
00
0'
#2052
1/
14
15
#2053
0.
02
#2054
1'
#2055
04
05
#2056
12
#2095
0#
#2096
1-
#2097
0,
#2098
1+
#2099
0*
#2100
1)
0!
#2101
10
#2102
0/
#2103
1.
#2150
1!
#2151
00
0'
#2152
1/
14
15
#2153
0.
02
#2154
1'
#2155
04
05
#2156
12
#2195
0"
#2196
16
#2197
03
#2198
1(
#2200
0!
#2201
10
#2202
0/
#2203
1.
#2250
1!
#2251
00
0'
#2252
1/
14
15
#2253
0.
01
#2254
1'
17
#2255
04
05
0$
#2256
11
#2300
0!
#2301
10
#2302
0/
#2303
1.
#2350
1!
#2351
00
0'
#2352
1/
14
15
#2353
0.
01
#2354
1'
#2355
04
05
#2356
11
#2400
0!
#2401
10
#2402
0/
#2403
1.
#2450
1!
#2451
00
0'
#2452
1/
14
15
#2453
0.
01
#2454
1'
#2455
04
05
#2456
11
#2500
0!
#2501
10
#2502
0/
#2503
1.
#2550
1!
#2551
00
0'
#2552
1/
14
15
#2553
0.
01
#2554
1'
#2555
04
05
#2556
11
#2595
1"
#2596
06
#2597
13
#2598
0(
#2600
0!
#2601
10
#2602
0/
#2603
1.
#2650
1!
#2651
00
0'
#2652
1/
14
15
#2653
0.
02
#2654
1'
1$
#2655
04
05
07
#2656
12
#2700
0!
#2701
10
#2702
0/
#2703
1.
#2750
1!
#2751
00
0'
#2752
1/
14
15
#2753
0.
02
#2754
1'
#2755
04
05
#2756
12
#2800
0!
#2801
10
#2802
0/
#2803
1.
#2845
0"
#2846
16
#2847
03
#2848
1(
#2850
1!
#2851
00
0'
#2852
1/
14
15
#2853
0.
01
#2854
1'
17
#2855
04
05
0$
#2856
11
#2900
0!
#2901
10
#2902
0/
#2903
1.
#2950
1!
#2951
00
0'
#2952
1/
14
15
#2953
0.
01
#2954
1'
#2955
04
05
#2956
11
#3000
0!
#3001
10
#3002
0/
#3003
1.
#3050
1!
#3051
00
0'
#3052
1/
14
15
#3053
0.
01
#3054
1'
#3055
04
05
#3056
11
#3100
0!
#3101
10
#3102
0/
#3103
1.
#3150
1!
#3151
00
0'
#3152
1/
14
15
#3153
0.
01
#3154
1'
#3155
04
05
#3156
11
#3200
0!
#3201
10
#3202
0/
#3203
1.
#3250
1!
#3251
00
0'
#3252
1/
14
15
#3253
0.
01
#3254
1'
#3255
04
05
#3256
11
#3300
0!
#3301
10
#3302
0/
#3303
1.
#3315
1"
#3316
06
#3317
13
#3318
0(
#3350
1!
#3351
00
0'
#3352
1/
14
15
#3353
0.
02
#3354
1'
1$
#3355
04
05
07
#3356
12
#3400
0!
#3401
10
#3402
0/
#3403
1.
#3450
1!
#3451
00
0'
#3452
1/
14
15
#3453
0.
02
#3454
1'
#3455
04
05
#3456
12
#3500
0!
#3501
10
#3502
0/
#3503
1.
#3525
0"
#3526
16
#3527
03
#3528
1(
#3550
1!
#3551
00
0'
#3552
1/
14
15
#3553
0.
01
#3554
1'
17
#3555
04
05
0$
#3556
11
#3600
0!
#3601
10
#3602
0/
#3603
1.
#3650
1!
#3651
00
0'
#3652
1/
14
15
#3653
0.
01
#3654
1'
#3655
04
05
#3656
11
#3700
0!
#3701
10
#3702
0/
#3703
1.
#3750
1!
#3751
00
0'
#3752
1/
14
15
#3753
0.
01
#3754
1'
#3755
04
05
#3756
11
#3800
0!
#3801
10
#3802
0/
#3803
1.
#3850
1!
#3851
00
0'
#3852
1/
14
15
#3853
0.
01
#3854
1'
#3855
04
05
#3856
11
#3872
1"
