OnlyNandYosysSynth/test/NAND.v
module NAND(
    input wire A,
    input wire B,
    output wire Y
);

assign #1 Y = ~(A&B);

endmodule

OnlyNandYosysSynth/test/synth_inverter.v
/* Generated by Yosys 0.9 (git sha1 1979e0b) */

(* top =  1  *)
(* src = "inverter.v:1" *)
module inverter(in, out);
  (* src = "inverter.v:2" *)
  input in;
  (* src = "inverter.v:3" *)
  output out;
  (* module_not_derived = 32'd1 *)
  (* src = "all2nand.v:3" *)
  NAND _0_ (
    .A(in),
    .B(in),
    .Y(out)
  );
endmodule

OnlyNandYosysSynth/test/inverter_tb.v
//iverilog -o .\out\inverter_tb .\inverter_tb.v .\synth_inverter.v .\DFF_PP0.v .\NOT.v .\NAND.v
module inverter_tb;
    reg in;

    inverter inv(in, out);
    
    initial begin
        $dumpfile("inverter.vcd");
        $dumpvars(1,inv);
        $display("start");
        in=1;
        #50;
        in=0;
        #50;
        in=1;
        #50;
        in=0;
        #50;
        in=1;
        $display("finish");
        $finish;
    end
endmodule

OnlyNandYosysSynth/test/out/inverter.vcd
$date
	Fri Aug 25 10:02:10 2023
$end
$version
	Icarus Verilog
$end
$timescale
	1s
$end
$scope module inverter_tb $end
$scope module inv $end
$var wire 1 ! in $end
$var wire 1 " out $end
$upscope $end
$upscope $end
$enddefinitions $end
$comment Show the parameter values. $end
$dumpall
$end
#0
$dumpvars
x"
1!
$end
#1
0"
#50
0!
#51
1"
#100
1!
#101
0"
#150
0!
#151
1"
#200
1!
